Workbook

Sheet Master Targets
A1: Master Target Database
A2: All 74 targets across the IB, Corp Dev, and VC lanes in one view | CBS Class of 2028 | Compiled and expanded Aug 22, 2026
A3: Priority / Status / Next Step mirror the lane tabs live: edit them THERE (yellow columns), not here. Sort or filter this sheet freely; formulas follow. | G3: Targets: | H3: =COUNTA($A$6:$A$79) -> 74 | I3: High priority: | J3: =COUNTIF($I$6:$I$79,"High") -> 0 | K3: In motion: | L3: =SUMPRODUCT(--($J$6:$J$79<>""))-COUNTIF($J$6:$J$79,"Not started")-COUNTIF($J$6:$J$79,"Pass") -> 0
A5: Target | B5: Lane | C5: Tier / Category | D5: HQ | E5: Edge in One Line | F5: Access Channel | G5: Timing | H5: Personal Angle | I5: Priority | J5: Status | K5: Next Step | L5: Next Step Date
A6: PJT Partners | B6: IB | C6: 1 - OCR | D6: New York | E6: Payward's house bank (NinjaTrader, Bitnomial, Reap) plus Core Scientific debtor mandate and $9B co-sell to CoreWeave | F6: OCR presentations and closed lists; RSSG restructuring is a separate MBA-heavy track | G6: Sept-Jan OCR | H6: You are living the process they sell; pitch market-structure conviction, not one client | I6: =IF('IB Targets'!F7="","",'IB Targets'!F7) | J6: =IF('IB Targets'!G7="","",'IB Targets'!G7) | K6: =IF('IB Targets'!K7="","",'IB Targets'!K7) | L6: =IF('IB Targets'!L7="","",'IB Targets'!L7)
A7: Evercore | B7: IB | C7: 1 - OCR | D7: New York | E7: Co-lead FA to Siris on the $4.2B Equiniti sale; largest EB associate class, best raw odds | F7: OCR; consistent CBS hirer | G7: Sept-Jan OCR | H7: Brand plus optionality play; Gol/Smiles is the anchor story | I7: =IF('IB Targets'!F8="","",'IB Targets'!F8) | J7: =IF('IB Targets'!G8="","",'IB Targets'!G8) | K7: =IF('IB Targets'!K8="","",'IB Targets'!K8) | L7: =IF('IB Targets'!L8="","",'IB Targets'!L8)
A8: Moelis | B8: IB | C8: 1 - OCR | D8: New York | E8: Restructuring franchise leader (Voyager, Genesis, BlockFi debtors); Bitfarms buy-side; Core Scientific co-sell | F8: Standard OCR process | G8: Sept-Jan OCR | H8: Rx depth is the counter-cyclical hedge if crypto M&A slows | I8: =IF('IB Targets'!F9="","",'IB Targets'!F9) | J8: =IF('IB Targets'!G9="","",'IB Targets'!G9) | K8: =IF('IB Targets'!K9="","",'IB Targets'!K9) | L8: =IF('IB Targets'!L9="","",'IB Targets'!L9)
A9: Centerview | B9: IB | C9: 1 - OCR | D9: New York | E9: Celsius Ch. 11 debtor banker (~$20M fee allocation); smallest class, most selective | F9: OCR | G9: Sept-Jan OCR | H9: - | I9: =IF('IB Targets'!F10="","",'IB Targets'!F10) | J9: =IF('IB Targets'!G10="","",'IB Targets'!G10) | K9: =IF('IB Targets'!K10="","",'IB Targets'!K10) | L9: =IF('IB Targets'!L10="","",'IB Targets'!L10)
A10: Perella Weinberg | B10: IB | C10: 1 - OCR | D10: New York | E10: FTX debtors and Celsius creditors: the two biggest crypto estates | F10: OCR | G10: Sept-Jan OCR | H10: Ask how the market-structure franchise carries forward post-FTX | I10: =IF('IB Targets'!F11="","",'IB Targets'!F11) | J10: =IF('IB Targets'!G11="","",'IB Targets'!G11) | K10: =IF('IB Targets'!K11="","",'IB Targets'!K11) | L10: =IF('IB Targets'!L11="","",'IB Targets'!L11)
A11: Lazard | B11: IB | C11: 1 - OCR | D11: New York | E11: Co-FA to FTAI on the $1.5B Long Ridge sale to MARA | F11: OCR | G11: Sept-Jan OCR | H11: - | I11: =IF('IB Targets'!F12="","",'IB Targets'!F12) | J11: =IF('IB Targets'!G12="","",'IB Targets'!G12) | K11: =IF('IB Targets'!K12="","",'IB Targets'!K12) | L11: =IF('IB Targets'!L12="","",'IB Targets'!L12)
A12: Houlihan Lokey | B12: IB | C12: 1 - OCR | D12: NYC + LA | E12: Genesis creditors; creditor-side franchise across the 2022-24 crypto bankruptcies | F12: OCR; corporate finance and restructuring tracks | G12: Sept-Jan OCR | H12: - | I12: =IF('IB Targets'!F13="","",'IB Targets'!F13) | J12: =IF('IB Targets'!G13="","",'IB Targets'!G13) | K12: =IF('IB Targets'!K13="","",'IB Targets'!K13) | L12: =IF('IB Targets'!L13="","",'IB Targets'!L13)
A13: Guggenheim | B13: IB | C13: 1 - OCR | D13: New York | E13: Fintech coverage; no disclosed crypto M&A credits 2024-26 | F13: OCR | G13: Sept-Jan OCR | H13: Weakest Tier 1 evidence; only if networking comes cheap | I13: =IF('IB Targets'!F14="","",'IB Targets'!F14) | J13: =IF('IB Targets'!G14="","",'IB Targets'!G14) | K13: =IF('IB Targets'!K14="","",'IB Targets'!K14) | L13: =IF('IB Targets'!L14="","",'IB Targets'!L14)
A14: Jefferies | B14: IB | C14: 1 - OCR | D14: New York | E14: Three sell-sides in 15 months (NinjaTrader, Kiavi, Long Ridge) plus FTX creditors; best evidence-to-odds ratio | F14: OCR; larger associate class than the EBs | G14: Sept-Jan OCR | H14: Their sell-side seats mirror your COR PRIME work from the client side | I14: =IF('IB Targets'!F15="","",'IB Targets'!F15) | J14: =IF('IB Targets'!G15="","",'IB Targets'!G15) | K14: =IF('IB Targets'!K15="","",'IB Targets'!K15) | L14: =IF('IB Targets'!L15="","",'IB Targets'!L15)
A15: Cantor Fitzgerald | B15: IB | C15: 2 - Direct | D15: New York | E15: DAT and de-SPAC co-leader (Twenty One, Securitize) plus Strive buy-side on the $1.4B Semler merger | F15: NYC postings plus direct outreach to the digital assets group | G15: Rolling | H15: Name the Semler mandate in the first note | I15: =IF('IB Targets'!F16="","",'IB Targets'!F16) | J15: =IF('IB Targets'!G16="","",'IB Targets'!G16) | K15: =IF('IB Targets'!K16="","",'IB Targets'!K16) | L15: =IF('IB Targets'!L16="","",'IB Targets'!L16)
A16: FT Partners | B16: IB | C16: 2 - Direct | D16: San Francisco (NYC + London) | E16: #1 crypto sell-side franchise: Deribit, Hidden Road, WonderFi, Equiniti co-lead | F16: Direct via Greenhouse plus outreach to the crypto vertical (founder-led: Steve McLaughlin) | G16: Rolling, post-IBC book | H16: You have built the models their decks run on; diligence the culture with former juniors first | I16: =IF('IB Targets'!F17="","",'IB Targets'!F17) | J16: =IF('IB Targets'!G17="","",'IB Targets'!G17) | K16: =IF('IB Targets'!K17="","",'IB Targets'!K17) | L16: =IF('IB Targets'!L17="","",'IB Targets'!L17)
A17: KBW (Stifel) | B17: IB | C17: 2 - Direct | D17: New York | E17: Stifel advised Riot on Block Mining; KBW crypto skews research and capital markets | F17: Network via FIG alumni | G17: Rolling | H17: Bank-crypto convergence (charters, stablecoin issuers) could re-rate this seat fast | I17: =IF('IB Targets'!F18="","",'IB Targets'!F18) | J17: =IF('IB Targets'!G18="","",'IB Targets'!G18) | K17: =IF('IB Targets'!K18="","",'IB Targets'!K18) | L17: =IF('IB Targets'!L18="","",'IB Targets'!L18)
... A28: Aream & Co | B28: IB | C28: 3 - Network | D28: London | E28: London digital asset boutique; no disclosed 2024-26 mandates surfaced | F28: Network | G28: Opportunistic | H28: Direct London-network play | I28: =IF('IB Targets'!F29="","",'IB Targets'!F29) | J28: =IF('IB Targets'!G29="","",'IB Targets'!G29) | K28: =IF('IB Targets'!K29="","",'IB Targets'!K29) | L28: =IF('IB Targets'!L29="","",'IB Targets'!L29)
A29: Kraken / Payward | B29: Corp Dev | C29: Exchange | D29: SF / remote-first | E29: Most acquisitive buyer in the dataset: 8+ deals in 18 months | F29: Ecosystem network; watch strategy and corp dev postings around the listing | G29: IPO window | H29: Your CoS and interim-CFO-style work is the job description | I29: =IF('Corp Dev Targets'!F6="","",'Corp Dev Targets'!F6) | J29: =IF('Corp Dev Targets'!G6="","",'Corp Dev Targets'!G6) | K29: =IF('Corp Dev Targets'!K6="","",'Corp Dev Targets'!K6) | L29: =IF('Corp Dev Targets'!L6="","",'Corp Dev Targets'!L6)
A30: Coinbase | B30: Corp Dev | C30: Exchange | D30: Remote-first | E30: Deribit ($2.9B) plus banker-less bolt-ons; corp dev and ventures are one org | F30: Fall MBA internship applications plus alumni | G30: Fall cycle | H30: Study the Coinbase Ventures portfolio before interviews | I30: =IF('Corp Dev Targets'!F7="","",'Corp Dev Targets'!F7) | J30: =IF('Corp Dev Targets'!G7="","",'Corp Dev Targets'!G7) | K30: =IF('Corp Dev Targets'!K7="","",'Corp Dev Targets'!K7) | L30: =IF('Corp Dev Targets'!L7="","",'Corp Dev Targets'!L7)
A31: Stripe | B31: Corp Dev | C31: Payments | D31: SF / Dublin | E31: Bridge ($1.1B) and Privy with no bankers disclosed; stablecoin thesis | F31: Warm intros only; no MBA machine | G31: Two-year project | H31: Payments and tokenization story; treat as a relationship build | I31: =IF('Corp Dev Targets'!F8="","",'Corp Dev Targets'!F8) | J31: =IF('Corp Dev Targets'!G8="","",'Corp Dev Targets'!G8) | K31: =IF('Corp Dev Targets'!K8="","",'Corp Dev Targets'!K8) | L31: =IF('Corp Dev Targets'!L8="","",'Corp Dev Targets'!L8)
A32: Ripple | B32: Corp Dev | C32: Infra / Payments | D32: SF (NYC office) | E32: Hidden Road ($1.25B), GTreasury ($1B), Rail, BC Payments; a deal a quarter | F32: Postings plus network; integration experience is the wedge | G32: Rolling | H32: Your Optimus integration work maps directly; prime-brokerage fluency from COR PRIME | I32: =IF('Corp Dev Targets'!F9="","",'Corp Dev Targets'!F9) | J32: =IF('Corp Dev Targets'!G9="","",'Corp Dev Targets'!G9) | K32: =IF('Corp Dev Targets'!K9="","",'Corp Dev Targets'!K9) | L32: =IF('Corp Dev Targets'!L9="","",'Corp Dev Targets'!L9)
A33: Mastercard | B33: Corp Dev | C33: TradFi | D33: Purchase, NY | E33: BVNK up to $1.8B, its biggest crypto deal; Start Path accelerator | F33: Structured MBA recruiting; corp dev and strategy tracks | G33: Fall cycle | H33: Most CBS-accessible corp dev door | I33: =IF('Corp Dev Targets'!F10="","",'Corp Dev Targets'!F10) | J33: =IF('Corp Dev Targets'!G10="","",'Corp Dev Targets'!G10) | K33: =IF('Corp Dev Targets'!K10="","",'Corp Dev Targets'!K10) | L33: =IF('Corp Dev Targets'!L10="","",'Corp Dev Targets'!L10)
A34: Robinhood | B34: Corp Dev | C34: Broker | D34: Menlo Park | E34: Bitstamp, WonderFi, TradePMR; outside banks plus inside corp dev | F34: Postings plus network | G34: Rolling | H34: - | I34: =IF('Corp Dev Targets'!F11="","",'Corp Dev Targets'!F11) | J34: =IF('Corp Dev Targets'!G11="","",'Corp Dev Targets'!G11) | K34: =IF('Corp Dev Targets'!K11="","",'Corp Dev Targets'!K11) | L34: =IF('Corp Dev Targets'!L11="","",'Corp Dev Targets'!L11)
A35: Circle | B35: Corp Dev | C35: Stablecoin | D35: New York (One WTC) | E35: Hashnote and infrastructure bolt-ons; public-company stablecoin consolidation mandate | F35: Postings plus NYC network | G35: Rolling | H35: Stablecoin thesis plus your regulated-product operating history | I35: =IF('Corp Dev Targets'!F12="","",'Corp Dev Targets'!F12) | J35: =IF('Corp Dev Targets'!G12="","",'Corp Dev Targets'!G12) | K35: =IF('Corp Dev Targets'!K12="","",'Corp Dev Targets'!K12) | L35: =IF('Corp Dev Targets'!L12="","",'Corp Dev Targets'!L12)
A36: Figure | B36: Corp Dev | C36: Tokenization | D36: San Francisco | E36: Kiavi ($717M) with Sixth Street; tokenization consolidator | F36: Network via the Kiavi advisor web | G36: Deal-driven | H36: Your ETC Group equity-tokenization platform work is directly relevant | I36: =IF('Corp Dev Targets'!F13="","",'Corp Dev Targets'!F13) | J36: =IF('Corp Dev Targets'!G13="","",'Corp Dev Targets'!G13) | K36: =IF('Corp Dev Targets'!K13="","",'Corp Dev Targets'!K13) | L36: =IF('Corp Dev Targets'!L13="","",'Corp Dev Targets'!L13)
A37: Talos | B37: Corp Dev | C37: Infra (FROZEN) | D37: New York | E37: Cloudwall, Skolem, D3X, Coin Metrics; principal-to-principal, no bankers ever disclosed | F37: POST-CLOSE ONLY: no contact while Project Optimus is live | G37: After Optimus close | H37: The warmest door available afterward; total discipline until signing | I37: =IF('Corp Dev Targets'!F14="","",'Corp Dev Targets'!F14) | J37: =IF('Corp Dev Targets'!G14="","",'Corp Dev Targets'!G14) | K37: =IF('Corp Dev Targets'!K14="","",'Corp Dev Targets'!K14) | L37: =IF('Corp Dev Targets'!L14="","",'Corp Dev Targets'!L14)
A38: Tether | B38: Corp Dev | C38: Stablecoin | D38: El Salvador | E38: Tether Investments: Adecoagro ~70%, Twenty One, mining/AI; largest strategic balance sheet in crypto | F38: Network-only; no conventional corp dev path | G38: Opportunistic | H38: Adecoagro = Brazil-agri + your LatAm M&A lens | I38: =IF('Corp Dev Targets'!F15="","",'Corp Dev Targets'!F15) | J38: =IF('Corp Dev Targets'!G15="","",'Corp Dev Targets'!G15) | K38: =IF('Corp Dev Targets'!K15="","",'Corp Dev Targets'!K15) | L38: =IF('Corp Dev Targets'!L15="","",'Corp Dev Targets'!L15)
A39: Anchorage Digital | B39: Corp Dev | C39: Crypto bank | D39: San Francisco | E39: OCC charter moat; Mountain Protocol (USDM) buy 2025 | F39: Postings + network | G39: Rolling | H39: Charter-bank language matches your regulated-platform seat | I39: =IF('Corp Dev Targets'!F16="","",'Corp Dev Targets'!F16) | J39: =IF('Corp Dev Targets'!G16="","",'Corp Dev Targets'!G16) | K39: =IF('Corp Dev Targets'!K16="","",'Corp Dev Targets'!K16) | L39: =IF('Corp Dev Targets'!L16="","",'Corp Dev Targets'!L16)
A40: FalconX | B40: Corp Dev | C40: Prime broker | D40: San Mateo, CA | E40: Serial: Arbelos 2025; 21Shares deal agreed Oct 2025 (verify close) | F40: Postings + network | G40: Rolling | H40: Prime brokerage + ETP: both your worlds in one seat | I40: =IF('Corp Dev Targets'!F17="","",'Corp Dev Targets'!F17) | J40: =IF('Corp Dev Targets'!G17="","",'Corp Dev Targets'!G17) | K40: =IF('Corp Dev Targets'!K17="","",'Corp Dev Targets'!K17) | L40: =IF('Corp Dev Targets'!L17="","",'Corp Dev Targets'!L17)
... A52: Digital Asset (Canton) | B52: Corp Dev | C52: Market infra | D52: New York | E52: Canton Network; institutional consortium | F52: Institutional hiring; NYC | G52: Rolling | H52: Post-trade market structure | I52: =IF('Corp Dev Targets'!F29="","",'Corp Dev Targets'!F29) | J52: =IF('Corp Dev Targets'!G29="","",'Corp Dev Targets'!G29) | K52: =IF('Corp Dev Targets'!K29="","",'Corp Dev Targets'!K29) | L52: =IF('Corp Dev Targets'!L29="","",'Corp Dev Targets'!L29)
A53: Galaxy Ventures | B53: VC | C53: One-roof | D53: New York | E53: Fund I $175M+ (Jun 2025); stablecoins, payments, tokenization thesis | F53: Same relationship as Galaxy IB; CVF-compatible | G53: CVF Sept; rolling | H53: Your exit comps are their underwriting; one Galaxy relationship, three doors | I53: =IF('VC Targets'!F6="","",'VC Targets'!F6) | J53: =IF('VC Targets'!G6="","",'VC Targets'!G6) | K53: =IF('VC Targets'!K6="","",'VC Targets'!K6) | L53: =IF('VC Targets'!L6="","",'VC Targets'!L6)
A54: Fintech Collective | B54: VC | C54: Fintech VC | D54: New York | E54: Best pure stablecoins/payments thesis fit in NYC; capital markets DNA | F54: Newsletter, Layer One podcast, Stablecon | G54: Rolling | H54: Their capital-markets DNA matches your prime-lending seat | I54: =IF('VC Targets'!F7="","",'VC Targets'!F7) | J54: =IF('VC Targets'!G7="","",'VC Targets'!G7) | K54: =IF('VC Targets'!K7="","",'VC Targets'!K7) | L54: =IF('VC Targets'!L7="","",'VC Targets'!L7)
A55: Archetype | B55: VC | C55: Independent | D55: New York | E55: Fund III $100M+ (Sep 2025); stablecoins, payments infra, crypto x AI | F55: Archebyte podcast, NYC in-person events | G55: Rolling | H55: - | I55: =IF('VC Targets'!F8="","",'VC Targets'!F8) | J55: =IF('VC Targets'!G8="","",'VC Targets'!G8) | K55: =IF('VC Targets'!K8="","",'VC Targets'!K8) | L55: =IF('VC Targets'!L8="","",'VC Targets'!L8)
A56: Variant | B56: VC | C56: Independent | D56: Brooklyn | E56: Variant 4 $222M (Jun 2026); crypto x AI autonomy thesis | F56: Thesis essays; writing-first outreach works here | G56: Rolling | H56: Write your way in; they reward essays | I56: =IF('VC Targets'!F9="","",'VC Targets'!F9) | J56: =IF('VC Targets'!G9="","",'VC Targets'!G9) | K56: =IF('VC Targets'!K9="","",'VC Targets'!K9) | L56: =IF('VC Targets'!L9="","",'VC Targets'!L9)
A57: CoinFund | B57: VC | C57: Independent | D57: Brooklyn | E57: $550M+ across recent vehicles; venture plus liquid; market-structure focus | F57: NYC events plus CVF; research and podcast engagement | G57: CVF Sept | H57: One of the few crypto funds a CBS student can see weekly | I57: =IF('VC Targets'!F10="","",'VC Targets'!F10) | J57: =IF('VC Targets'!G10="","",'VC Targets'!G10) | K57: =IF('VC Targets'!K10="","",'VC Targets'!K10) | L57: =IF('VC Targets'!L10="","",'VC Targets'!L10)
A58: Portal Ventures | B58: VC | C58: Independent | D58: New York | E58: Fund II $75M (late 2024); pre-seed lead checks; fundamentals-driven | F58: Fisher's writing and podcasts; MBA-friendly framing | G58: Rolling | H58: The most MBA-legible framing in the set; hires early-career | I58: =IF('VC Targets'!F11="","",'VC Targets'!F11) | J58: =IF('VC Targets'!G11="","",'VC Targets'!G11) | K58: =IF('VC Targets'!K11="","",'VC Targets'!K11) | L58: =IF('VC Targets'!L11="","",'VC Targets'!L11)
A59: VanEck Ventures | B59: VC | C59: Corporate fund | D59: New York | E59: $30M debut fund; ex-Circle Ventures team; stablecoin/tokenization thesis | F59: Media-active partners; direct outreach viable | G59: Rolling | H59: An ETP operator's story lands at an ETP house: your ETC Group years are the intro | I59: =IF('VC Targets'!F12="","",'VC Targets'!F12) | J59: =IF('VC Targets'!G12="","",'VC Targets'!G12) | K59: =IF('VC Targets'!K12="","",'VC Targets'!K12) | L59: =IF('VC Targets'!L12="","",'VC Targets'!L12)
A60: 6th Man Ventures | B60: VC | C60: Independent | D60: New York | E60: Fund II $145M; consumer and Solana-weighted | F60: Dudas is highly public; NYC events | G60: Rolling | H60: - | I60: =IF('VC Targets'!F13="","",'VC Targets'!F13) | J60: =IF('VC Targets'!G13="","",'VC Targets'!G13) | K60: =IF('VC Targets'!K13="","",'VC Targets'!K13) | L60: =IF('VC Targets'!L13="","",'VC Targets'!L13)
A61: North Island Ventures | B61: VC | C61: Independent | D61: New York | E61: ~$300M AUM; stablecoin payments and interoperability thesis | F61: Scher podcasts; watch for associate openings | G61: Rolling | H61: A live seat to watch, not just a coffee: they have hired associates | I61: =IF('VC Targets'!F14="","",'VC Targets'!F14) | J61: =IF('VC Targets'!G14="","",'VC Targets'!G14) | K61: =IF('VC Targets'!K14="","",'VC Targets'!K14) | L61: =IF('VC Targets'!L14="","",'VC Targets'!L14)
A62: Dragonfly (NYC) | B62: VC | C62: Bicoastal | D62: NYC + Singapore | E62: Fund IV $650M (Feb 2026); RWA and stablecoin pivot; ~$4B AUM | F62: Chopping Block podcast, research | G62: Rolling | H62: Note the DOJ / Tornado Cash caveat on one GP before any outreach there | I62: =IF('VC Targets'!F15="","",'VC Targets'!F15) | J62: =IF('VC Targets'!G15="","",'VC Targets'!G15) | K62: =IF('VC Targets'!K15="","",'VC Targets'!K15) | L62: =IF('VC Targets'!L15="","",'VC Targets'!L15)
A63: Union Square Ventures | B63: VC | C63: Independent | D63: New York | E63: Thesis-driven; early Coinbase backer; still leading crypto rounds in 2025 | F63: CVF plus thoughtful written outreach; they reward writing | G63: CVF Sept | H63: - | I63: =IF('VC Targets'!F16="","",'VC Targets'!F16) | J63: =IF('VC Targets'!G16="","",'VC Targets'!G16) | K63: =IF('VC Targets'!K16="","",'VC Targets'!K16) | L63: =IF('VC Targets'!L16="","",'VC Targets'!L16)
A64: Castle Island Ventures | B64: VC | C64: Independent | D64: Boston | E64: Backed both Talos and Coin Metrics; infrastructure-focused early stage | F64: Engage On The Brink first; post-close Talos angle | G64: Post-close | H64: The fund behind your counterparty; likely your strongest single VC relationship | I64: =IF('VC Targets'!F17="","",'VC Targets'!F17) | J64: =IF('VC Targets'!G17="","",'VC Targets'!G17) | K64: =IF('VC Targets'!K17="","",'VC Targets'!K17) | L64: =IF('VC Targets'!L17="","",'VC Targets'!L17)
... A79: Index Ventures | B79: VC | C79: Generalist w/ crypto | D79: SF + NYC + London | E79: Bridge (-> Stripe $1.1B) credential; fintech bench | F79: NYC office network | G79: Rolling | H79: Stablecoin credential; verify current appetite | I79: =IF('VC Targets'!F32="","",'VC Targets'!F32) | J79: =IF('VC Targets'!G32="","",'VC Targets'!G32) | K79: =IF('VC Targets'!K32="","",'VC Targets'!K32) | L79: =IF('VC Targets'!L32="","",'VC Targets'!L32)
A81: Static columns compiled Aug 22, 2026 from the lane tabs, Target Profiles, and the NYC fund research. The 27 targets promoted the same day (universe + NYC-presence waves) and several HQ entries come from general knowledge - confirm before citing. Priority / Status / Next Step are live formulas into the lane tabs; keep working there. Full universes with NYC-presence flags: Corp Dev Universe and VC Universe tabs.

Sheet IB Targets
A1: IB / M&A Advisory Targets
A2: CBS Class of 2028 | Summer 2027 associate cycle | Tiers: 1 OCR, 2 Direct, 3 Network | Depth on Target Profiles
A3: Fill in the yellow columns (F to M). Row 6 is an example row; overwrite or delete it. | H3: Targets: | I3: =COUNTA($A$7:$A$29) -> 23 | J3: High priority: | K3: =COUNTIF($F$7:$F$29,"High") -> 0 | L3: In motion: | M3: =COUNTA($G$7:$G$29)-COUNTIF($G$7:$G$29,"Not started")-COUNTIF($G$7:$G$29,"Pass") -> 0
A5: Firm | B5: Tier | C5: Crypto / Deal Evidence | D5: Hiring Model | E5: Access Channel | F5: Priority | G5: Status | H5: Contact(s) | I5: Contact Source | J5: Last Contact | K5: Next Step | L5: Next Step Date | M5: Notes
A6: (Example) Firm Name | B6: 1 - OCR | C6: Example row: overwrite or delete | D6: Structured | E6: OCR | F6: High | G6: Outreach sent | H6: Jane Doe, VP FIG | I6: CBS alum ('24) | J6: 46280 | K6: Coffee chat at EIS | L6: 46287 | M6: Met at fintech club event
A7: PJT Partners | B7: 1 - OCR | C7: Payward's house bank (NinjaTrader buy, Bitnomial sell, Reap buy); Core Scientific debtor banker and co-sell to CoreWeave ($9B) | D7: Structured summer associate program | E7: OCR presentations and closed lists; RSSG restructuring track is MBA-heavy
A8: Evercore | B8: 1 - OCR | C8: Co-lead FA to Siris on the $4.2B Equiniti sale; broad fintech franchise | D8: Structured summer associate program | E8: Core OCR name; consistent CBS hirer
A9: Moelis | B9: 1 - OCR | C9: Restructuring franchise leader (Voyager, Genesis, BlockFi debtors); Bitfarms buy-side; Core Scientific co-sell | D9: Structured summer associate program | E9: Standard OCR process
A10: Centerview | B10: 1 - OCR | C10: Celsius Chapter 11 debtor banker (largest banker fee allocation, ~$20M); top-end fintech | D10: Structured summer associate program | E10: OCR; smallest class, most selective of the group
A11: Perella Weinberg | B11: 1 - OCR | C11: FTX debtors banker; Celsius creditors banker; two of the biggest crypto estates | D11: Structured summer associate program | E11: OCR
A12: Lazard | B12: 1 - OCR | C12: Co-FA to FTAI on the $1.5B Long Ridge sale to MARA | D12: Structured summer associate program | E12: OCR
A13: Houlihan Lokey | B13: 1 - OCR | C13: Genesis creditors banker; creditor-side franchise across the crypto bankruptcies | D13: Structured summer associate program | E13: OCR; corporate finance and restructuring tracks
A14: Guggenheim | B14: 1 - OCR | C14: Fintech coverage; no disclosed crypto M&A credits surfaced 2024-26 | D14: Structured summer associate program | E14: OCR
A15: Jefferies | B15: 1 - OCR | C15: Three sell-sides in 15 months (NinjaTrader, Kiavi, FTAI/Long Ridge) plus FTX creditors committee; steadiest non-BB in the space | D15: Structured summer associate program | E15: OCR; larger associate class than the EBs
A16: Cantor Fitzgerald | B16: 2 - Direct | C16: DAT and de-SPAC co-leader (Twenty One, Securitize) plus buy-side FA to Strive on the $1.4B Semler merger; bitcoin financing | D16: Posts roles; less structured MBA path | E16: NYC postings plus direct outreach to the digital assets group
A17: FT Partners | B17: 2 - Direct | C17: #1 crypto sell-side franchise: Deribit, Hidden Road, WonderFi, and Equiniti co-lead; four marquee exits | D17: Direct hiring via Greenhouse; apprenticeship model | E17: Direct application plus targeted outreach; no major OCR presence
A18: KBW (Stifel) | B18: 2 - Direct | C18: Stifel advised Riot on the Block Mining buy; KBW crypto work skews research and capital markets, not M&A | D18: Mostly lateral; selective postings | E18: Network via FIG alumni
... A29: Aream & Co | B29: 3 - Network | C29: London digital asset boutique; no disclosed 2024-26 mandates surfaced in the research | D29: No formal program | E29: Network
A31: Deal evidence from press releases, firm tombstones, SEC filings, and Architect Partners alerts through Aug 21, 2026. Tier 1 runs on the Sept-Jan OCR cycle; Tiers 2 and 3 run rolling and post-close.

Sheet Corp Dev Targets
A1: Corporate Development Targets
A2: The buy side of your Deal Evidence tab | Just-in-time hiring; postings and network, not a cycle | Full acquirer universe on the Corp Dev Universe tab
A3: Fill in the yellow columns (F to M). | H3: Targets: | I3: =COUNTA($A$6:$A$29) -> 24 | J3: High priority: | K3: =COUNTIF($F$6:$F$29,"High") -> 0 | L3: In motion: | M3: =COUNTA($G$6:$G$29)-COUNTIF($G$6:$G$29,"Not started")-COUNTIF($G$6:$G$29,"Pass") -> 0
A5: Firm | B5: Category | C5: Crypto / Deal Evidence | D5: Hiring Model | E5: Access Channel | F5: Priority | G5: Status | H5: Contact(s) | I5: Contact Source | J5: Last Contact | K5: Next Step | L5: Next Step Date | M5: Notes
A6: Kraken / Payward | B6: Exchange | C6: Most acquisitive buyer in the dataset: 8+ deals in 18 months (NinjaTrader, Bitnomial, Reap, Small Exchange, Magna, Magic Labs, Breakout) | D6: Just-in-time; tiny team; pre-IPO equity | E6: Ecosystem network; watch strategy and corp dev postings around the listing
A7: Coinbase | B7: Exchange | C7: Deribit ($2.9B) plus banker-less bolt-ons (Echo, Liquifi, Iron, Spindl); corp dev and ventures combined | D7: Elite in-house shop; runs structured MBA internships | E7: Fall applications plus alumni
A8: Stripe | B8: Payments | C8: Bridge ($1.1B) and Privy with no bankers disclosed; stablecoin thesis | D8: Pure network hiring; no MBA machine | E8: Warm intros only; two-year relationship project
A9: Ripple | B9: Infra / Payments | C9: Hidden Road ($1.25B), GTreasury ($1B), Rail, BC Payments; a deal a quarter on a huge balance sheet | D9: Posts corp dev and integration roles | E9: Postings plus network; integration experience is the wedge
A10: Mastercard | B10: TradFi | C10: BVNK up to $1.8B, its biggest crypto deal; Start Path accelerator | D10: Structured MBA recruiting; corp dev and strategy tracks | E10: Most CBS-accessible corp dev door
A11: Robinhood | B11: Broker | C11: Bitstamp, WonderFi, TradePMR; uses Barclays and JPMorgan outside, corp dev inside | D11: Posts roles; growing team | E11: Postings plus network
A12: Circle | B12: Stablecoin | C12: Hashnote and infrastructure bolt-ons; public company with stablecoin consolidation mandate | D12: Small team; posts roles | E12: Postings plus NYC network
A13: Figure | B13: Tokenization | C13: Kiavi ($717M) with Sixth Street; tokenization consolidator | D13: Small team; deal-driven hiring | E13: Network via the Kiavi advisor web
A14: Talos | B14: Infra (frozen) | C14: Cloudwall, Skolem, D3X, Coin Metrics ($100M+); principal-to-principal, no bankers ever disclosed | D14: Tiny; hires around deals | E14: POST-CLOSE ONLY: no contact while Project Optimus is live; afterward the warmest door available
A15: Tether | B15: Stablecoin | C15: Tether Investments: Adecoagro ~70% tender ($615.5M), Twenty One, mining/AI/media bets; the largest strategic balance sheet in crypto | D15: No conventional corp dev path; network-only | E15: Strategic weight, not a hiring machine; Adecoagro = LatAm angle
A16: Anchorage Digital | B16: Crypto bank | C16: OCC-chartered digital asset bank; bought Mountain Protocol (USDM stablecoin, 2025); institutional custody/settlement | D16: Small corp dev; institutional hiring | E16: Postings + network; charter-bank story
A17: FalconX | B17: Prime broker | C17: Serial acquirer: Arbelos (2025); 21Shares acquisition agreed Oct 2025 (verify close); prime consolidation leader | D17: Real corp dev; growing fast | E17: Postings + network; prime + ETP = both your worlds
... A29: Digital Asset (Canton) | B29: Market infra | C29: NYC; Canton Network with a Goldman/DTCC-adjacent consortium; major 2025 raise | D29: Institutional hiring; NYC | E29: NYC TradFi-crypto door; post-trade + tokenization
A31: Corp dev teams are small (2 to 8 people) and hire around deals; the 'Not disclosed' buy-side cells in Deal Evidence mark the shops that run deals without bankers. Talos row is FROZEN until Project Optimus signs; no outreach of any kind before close. Rows 15-22 added Aug 22, 2026 from general knowledge (Jan 2026 horizon), not the verified research - verify before citing. Full acquirer universe on the Corp Dev Universe tab. Rows 23-29 added Aug 22, 2026 for NYC presence + fit (BlackRock through Digital Asset) - K-sourced except where research-verified; verify before citing.

Sheet Corp Dev Universe
A1: Corp Dev Universe
A2: The full strategic-acquirer universe with NYC reachability | Filter the NYC Presence column to plan coffee-chat range
A3: Src: R = verified Aug 2026 research; K = general knowledge - VERIFY. NYC Presence: HQ / Metro (commutable) / Office / Team / People (individuals based there) / Verify (unconfirmed) / '-' none known. K-confidence, Jan 2026 horizon - confirm before planning outreach around it. Yellow column M is yours. | H3: Entries: | I3: =COUNTA($A$6:$A$144) -> 139
A5: Company | B5: Category | C5: HQ | D5: NYC Presence | E5: Ownership / Ticker | F5: Crypto M&A / Strategic Evidence | G5: Corp Dev & Hiring Reality | H5: MBA Door | I5: Personal Angle | J5: Priority | K5: Src | L5: Notes | M5: Your Flag
A6: Kraken / Payward | B6: Exchange | C6: SF / remote-first | D6: People (verify) | E6: Private (IPO track) | F6: 8+ deals in 18 months: NinjaTrader $1.5B, Bitnomial, Reap, Small Exchange, Magna, Magic Labs, Breakout | G6: Just-in-time; tiny team; pre-IPO equity | H6: Ecosystem network + postings around listing | I6: CoS/interim-CFO profile matches | J6: S1 | K6: R | L6: On Corp Dev Targets tab; On working tab
A7: Coinbase | B7: Exchange | C7: Remote-first | D7: Office | E7: Public (COIN) | F7: Deribit $2.9B; banker-less bolt-ons: Echo, Liquifi, Iron, Spindl | G7: Elite in-house; structured MBA internships | H7: Fall applications + alumni | I7: Study Ventures portfolio first | J7: S1 | K7: R | L7: On Corp Dev Targets tab; On working tab
A8: Stripe | B8: Payments | C8: SF / Dublin | D8: Office | E8: Private | F8: Bridge $1.1B; Privy; stablecoin thesis | G8: Pure network hiring | H8: Warm intros only; 2-year project | I8: Tokenization + payments story | J8: S2 | K8: R | L8: On Corp Dev Targets tab; On working tab
A9: Ripple | B9: Infra / Payments | C9: SF (NYC office) | D9: Office | E9: Private | F9: Hidden Road $1.25B; GTreasury $1B; Rail $200M; BC Payments | G9: Posts corp dev + integration roles | H9: Postings + network | I9: Integration work maps; prime adjacency | J9: S1 | K9: R | L9: On Corp Dev Targets tab; On working tab
A10: Mastercard | B10: Payment network | C10: Purchase, NY | D10: Metro HQ (Purchase) | E10: Public (MA) | F10: BVNK up to $1.8B (closed Aug 2026); Start Path | G10: Structured MBA recruiting | H10: Most CBS-accessible corp dev door | I10: - | J10: S1 | K10: R | L10: On Corp Dev Targets tab; On working tab
A11: Robinhood | B11: Broker | C11: Menlo Park, CA | D11: Office | E11: Public (HOOD) | F11: Bitstamp $200M; WonderFi C$250M; TradePMR | G11: Posts roles; growing team | H11: Postings + network | I11: - | J11: S2 | K11: R | L11: On Corp Dev Targets tab; On working tab
A12: Circle | B12: Stablecoin | C12: New York (One WTC) | D12: HQ | E12: Public (CRCL) | F12: Hashnote; infrastructure bolt-ons; consolidation mandate | G12: Small team; posts roles | H12: Postings + NYC network | I12: Regulated-platform operating history | J12: S1 | K12: R | L12: On Corp Dev Targets tab; On working tab
A13: Figure | B13: Tokenization | C13: San Francisco, CA | D13: Office (verify) | E13: Public (FIGR, verify) | F13: Kiavi $717M with Sixth Street | G13: Small; deal-driven hiring | H13: Network via Kiavi advisor web | I13: ETC tokenization platform work | J13: S2 | K13: R | L13: On Corp Dev Targets tab; On working tab
A14: Talos | B14: Infra (FROZEN) | C14: New York, NY | D14: HQ | E14: Private | F14: Cloudwall, Skolem, D3X, Coin Metrics $100M+; principal-to-principal | G14: Tiny; hires around deals | H14: POST-CLOSE ONLY | I14: Warmest door after Optimus signs | J14: S1 | K14: R | L14: On Corp Dev Targets tab; frozen until close; On working tab
A15: Gemini | B15: Exchange | C15: New York, NY | D15: HQ | E15: Public (GEMI) | F15: IPO Sep 2025 ($425M); acquisitive historically (Nifty era); rebuilding | G15: Small corp dev; NYC HQ | H15: NYC postings + network | I15: Winklevoss Capital same roof | J15: S2 | K15: R | L15: Stock fell post-IPO; $100M insider injection May 2026
A16: Bullish | B16: Exchange / media | C16: NYC + Cayman | D16: HQ | E16: Public (BLSH, verify) | F16: Equiniti $4.2B buy (2026); owns CoinDesk | G16: Building out post-Equiniti | H16: Postings; the Equiniti integration needs people | I16: Integration story = your wedge | J16: S2 | K16: R | L16: Equiniti deal is in your Deal Evidence tab
A17: Crypto.com | B17: Exchange | C17: Singapore | D17: - | E17: Private | F17: Acquisitive history (Watchdog, derivatives licenses, SEC-reg entities) | G17: Global; US corp dev present | H17: Postings | I17: - | J17: S3 | K17: K
A18: OKX | B18: Exchange | C18: Seychelles / San Jose US HQ | D18: Office (verify) | E18: Private | F18: US expansion 2025; license-driven deals | G18: US build-out hiring | H18: US postings | I18: - | J18: S3 | K18: K
A19: eToro | B19: Broker | C19: Israel / NYC | D19: Office (US base) | E19: Public (ETOR) | F19: IPO May 2025; acquisitive history (Gatsby, Deep) | G19: Corp dev exists | H19: Postings | I19: - | J19: S3 | K19: K
A20: Webull | B20: Broker | C20: St. Petersburg, FL | D20: - | E20: Public (BULL) | F20: Re-launched crypto 2025 | G20: Thin crypto corp dev | H20: - | I20: - | J20: Monitor | K20: K
A21: Interactive Brokers | B21: Broker | C21: Greenwich, CT | D21: Metro (Greenwich) | E21: Public (IBKR) | F21: Crypto via Paxos/Zero Hash rails | G21: Strategy more than M&A | H21: Metro-area TradFi door | I21: - | J21: Monitor | K21: K
A22: Charles Schwab | B22: Broker | C22: Westlake, TX | D22: - (corp dev in TX) | E22: Public (SCHW) | F22: Announced direct crypto trading 2025-26; EDX backer | G22: Large corp dev/strategy org | H22: Structured hiring | I22: TradFi-crypto convergence seat | J22: S3 | K22: K
A23: Morgan Stanley / E*Trade | B23: Bank / broker | C23: New York, NY | D23: HQ | E23: Public (MS) | F23: E*Trade crypto launch announced (2025, Zero Hash rails - verify) | G23: Strategy org | H23: Classic MBA door | I23: Convergence thesis | J23: S3 | K23: K
A24: Coincheck Group | B24: Exchange | C24: Tokyo / Nasdaq | D24: - | E24: Public (CNCK) | F24: Aplo buy (2025, Galaxy sell-side); Nasdaq-listed via de-SPAC | G24: Small; Japan + EU | H24: - | I24: Aplo deal in Deal Evidence tab | J24: Monitor | K24: R
A25: Dunamu (Upbit) | B25: Exchange | C25: Seoul, KR | D25: - | E25: Private | F25: Korea's largest; occasional stakes | G25: Korea-based | H25: - | I25: - | J25: Monitor | K25: K
A26: bitFlyer | B26: Exchange | C26: Tokyo, JP | D26: - | E26: Private | F26: Acquired FTX Japan (2024) | G26: Japan | H26: - | I26: - | J26: Monitor | K26: K
A27: SBI Digital Asset Holdings | B27: Exchange / bank group | C27: Tokyo, JP | D27: - | E27: Public (8473.T) | F27: bitbank $289M (2026); B2C2 owner; serial digital-asset buyer | G27: Group-level corp dev | H27: - | I27: bitbank deal in Deal Evidence tab | J27: Monitor | K27: R
A28: Strike (Zap) | B28: Payments / bitcoin | C28: Chicago, IL | D28: - | E28: Private | F28: Jack Mallers; also CEO of Twenty One | G28: Tiny | H28: - | I28: - | J28: Monitor | K28: K
... A30: Block (Square) | B30: Fintech / bitcoin | C30: Oakland, CA | D30: People (verify) | E30: Public (XYZ) | F30: Bitkey, Proto mining rigs, Cash App bitcoin; Afterpay-era M&A muscle | G30: Real corp dev org | H30: Postings; bitcoin-native strategy roles | I30: - | J30: S2 | K30: K
A31: PayPal | B31: Payments | C31: San Jose, CA | D31: Office (Venmo NYC) | E31: Public (PYPL) | F31: PYUSD stablecoin; Curv + Paidy era buys; Ventures arm | G31: Large corp dev; MBA-friendly | H31: Structured recruiting | I31: Stablecoin distribution thesis | J31: S1 | K31: K | L31: Promoted to Corp Dev Targets tab; On working tab
A32: Visa | B32: Payment network | C32: San Francisco, CA | D32: Office | E32: Public (V) | F32: Stablecoin settlement (USDC); Pismo $1B (Brazil); crypto team under Cuy Sheffield | G32: Large corp dev + crypto team | H32: Structured MBA recruiting | I32: Pismo = Brazil angle; stablecoin settlement = thesis | J32: S1 | K32: K | L32: Promoted to Corp Dev Targets tab; On working tab
A33: Fiserv | B33: Payments infra | C33: Milwaukee, WI | D33: Office (First Data legacy) | E33: Public (FI) | F33: FIUSD stablecoin launch (2025); serial acquirer | G33: Big corp dev org | H33: Structured hiring | I33: Stablecoin-meets-legacy-rails story | J33: S3 | K33: K
A34: Western Union | B34: Remittances | C34: Denver, CO | D34: - | E34: Public (WU) | F34: Stablecoin pilots announced 2025 (verify scope) | G34: Corp dev exists | H34: - | I34: Remittance + stablecoin thesis | J34: Monitor | K34: K
A35: MoneyGram | B35: Remittances | C35: Dallas, TX | D35: - | E35: Private (MDP-owned) | F35: Stellar USDC cash rails | G35: - | H35: - | I35: - | J35: Monitor | K35: K
A36: Revolut | B36: Neobank | C36: London, UK | D36: Office (US base NYC) | E36: Private | F36: Large crypto book; occasional bolt-ons | G36: London strategy org | H36: London network | I36: Your London base | J36: S3 | K36: K
A37: Nubank | B37: Neobank | C37: Sao Paulo, BR | D37: - | E37: Public (NU) | F37: Crypto rollout; token bets; minority stakes | G37: Real corp dev; LatAm MBA hiring | H37: Structured + network | I37: Brazil: language, market, network | J37: S2 | K37: K | L37: Promoted to Corp Dev Targets tab; On working tab
A38: Mercado Libre / Mercado Pago | B38: Commerce / fintech | C38: Buenos Aires / Sao Paulo | D38: - | E38: Public (MELI) | F38: Crypto in Mercado Pago; stablecoin interest (Meli Dolar) | G38: Big corp dev; LatAm MBA recruiting | H38: Structured + network | I38: Brazil angle direct | J38: S3 | K38: K
A39: Bitso | B39: Exchange / payments | C39: Mexico City / remote | D39: - | E39: Private | F39: LatAm leader; stablecoin rails (Juno unit) | G39: Small corp dev | H39: Network | I39: LatAm crypto payments = your two worlds | J39: S3 | K39: K
A40: SoFi | B40: Fintech / bank | C40: San Francisco, CA | D40: Office | E40: Public (SOFI) | F40: Re-entered crypto 2025 with bank charter | G40: Corp dev + strategy org | H40: Postings | I40: Charter-bank crypto convergence | J40: S3 | K40: K
A41: dLocal | B41: Payments | C41: Montevideo, UY | D41: - | E41: Public (DLO) | F41: Stablecoin settlement interest (verify) | G41: - | H41: - | I41: LatAm payments | J41: Monitor | K41: K
A42: EBANX | B42: Payments | C42: Curitiba, BR | D42: - | E42: Private | F42: LatAm payments; stablecoin pilots (verify) | G42: - | H42: - | I42: Brazil HQ | J42: Monitor | K42: K
A43: Tether | B43: Stablecoin | C43: El Salvador | D43: - | E43: Private | F43: Tether Investments: Adecoagro ~70% ($615.5M tender), Twenty One, Rumble stake, mining, AI | G43: No conventional corp dev path; strategic weight enormous | H43: Network only; not a hiring machine | I43: Adecoagro = Brazil-agri + your LatAm M&A lens | J43: S2 | K43: R | L43: Promoted to Corp Dev Targets tab; Adecoagro in Deal Evidence; On working tab
A44: Paxos | B44: Stablecoin infra | C44: New York, NY | D44: HQ | E44: Private | F44: Issues PYUSD, USDG; regulated trust; acquisitive-adjacent (Membrane? verify) | G44: NYC; regulated-infra hiring | H44: NYC postings + network | I44: Regulated-platform language; Liberty City web | J44: S2 | K44: K | L44: On working tab
A45: BVNK | B45: Stablecoin payments | C45: London, UK | D45: Verify | E45: Mastercard (closed Aug 2026) | F45: Acquired by Mastercard up to $1.8B | G45: Integration phase | H45: Via Mastercard door | I45: London + stablecoin ops | J45: S3 | K45: R | L45: Deal in Deal Evidence tab
A46: Bridge (Stripe) | B46: Stablecoin infra | C46: SF (Stripe unit) | D46: - | E46: Stripe-owned | F46: Stripe's $1.1B stablecoin backbone | G46: Via Stripe | H46: Via Stripe lane | I46: - | J46: S3 | K46: R
A47: Zero Hash | B47: Crypto-as-a-service | C47: Chicago, IL | D47: Verify | E47: Private | F47: Powers brokers' crypto (IBKR, others); raised big 2025 (verify) | G47: B2B infra hiring | H47: Postings | I47: B2B rails = market structure | J47: S3 | K47: K
A48: MoonPay | B48: On-ramp / payments | C48: Miami, FL | D48: Office (verify) | E48: Private | F48: Serial acquirer: Helio ($175M), plus infra bolt-ons (verify list) | G48: Real corp dev activity | H48: Postings + network | I48: Serial-acquirer seat | J48: S2 | K48: K | L48: Promoted to Corp Dev Targets tab; On working tab
A49: Ramp Network | B49: On-ramp | C49: Warsaw / London | D49: - | E49: Private | F49: On/off-ramp infra | G49: - | H49: - | I49: - | J49: Monitor | K49: K
A50: Transak | B50: On-ramp | C50: Miami / London | D50: - | E50: Private | F50: On-ramp infra | G50: - | H50: - | I50: - | J50: Monitor | K50: K
A51: BitPay | B51: Crypto payments | C51: Atlanta, GA | D51: - | E51: Private | F51: OG crypto payments processor | G51: - | H51: - | I51: - | J51: Monitor | K51: K
A52: Ondo Finance | B52: Tokenization / RWA | C52: New York, NY | D52: HQ | E52: Token (ONDO) | F52: Oasis Pro buy (broker-dealer licenses, 2025); Strangelove; GM-cleared products | G52: Small; acquisitive for licenses | H52: NYC network | I52: Tokenized treasuries = thesis center | J52: S2 | K52: K | L52: On working tab
A53: Agora | B53: Stablecoin | C53: New York, NY | D53: HQ | E53: Private | F53: White-label stablecoin issuer; Dragonfly-backed | G53: Early-stage hiring | H53: NYC network | I53: Stablecoin issuance mechanics | J53: S3 | K53: K
A54: Superstate | B54: Tokenization | C54: Chicago / NYC | D54: Office | E54: Private | F54: Tokenized funds (Robert Leshner) | G54: Small | H54: Network | I54: - | J54: Monitor | K54: K
A55: BitGo | B55: Custody | C55: Palo Alto, CA | D55: Office (BitGo NY Trust) | E55: Private (IPO filed 2025, verify) | F55: Custody consolidator; HeightZero, Brassica buys (verify); IPO track | G55: Corp dev + strategy hiring on IPO path | H55: Postings | I55: Regulated custody = adjacent to prime | J55: S2 | K55: K | L55: On working tab
A56: Anchorage Digital | B56: Crypto bank / custody | C56: San Francisco, CA | D56: Office | E56: Private (OCC charter) | F56: Mountain Protocol (USDM stablecoin) buy 2025; federal charter moat | G56: Small corp dev; institutional hiring | H56: Postings + network | I56: Charter-bank language; prime adjacency | J56: S1 | K56: K | L56: Promoted to Corp Dev Targets tab; On working tab
A57: Fireblocks | B57: Infra / custody tech | C57: New York, NY | D57: HQ | E57: Private | F57: Serial buyer: BlockFold, First Digital? (verify list); tokenization push | G57: NYC HQ; real corp dev | H57: NYC postings + network | I57: Your COR PRIME stack likely runs on them | J57: S1 | K57: K | L57: Promoted to Corp Dev Targets tab; On working tab
A58: Copper | B58: Custody / prime infra | C58: London, UK | D58: Verify | E58: Private | F58: ClearLoop network; acquisitive-adjacent | G58: London institutional | H58: London network | I58: Direct competitor-adjacent to COR PRIME world | J58: S2 | K58: K
A59: Komainu | B59: Custody | C59: Jersey / London | D59: - | E59: Nomura JV | F59: Nomura-Ledger-CoinShares JV; raised 2024 | G59: Small | H59: Laser Digital web | I59: - | J59: S3 | K59: K
A60: Zodia Custody / Zodia Markets | B60: Custody / OTC | C60: London, UK | D60: - | E60: StanChart-built | F60: Zodia Custody minority buyout by StanChart (2026); Zodia Markets to Circle Ventures web (verify) | G60: Via SC Ventures | H60: - | I60: In Deal Evidence tab | J60: S3 | K60: R
A61: Hex Trust | B61: Custody | C61: Hong Kong / Dubai | D61: - | E61: Private | F61: Asia institutional custody | G61: - | H61: - | I61: - | J61: Monitor | K61: K
A62: Ledger | B62: Hardware / custody tech | C62: Paris, FR | D62: Office (verify) | E62: Private | F62: Enterprise + consumer custody tech | G62: Paris/London | H62: - | I62: - | J62: Monitor | K62: K
A63: Utila | B63: Wallet infra | C63: Tel Aviv / NYC | D63: Office | E63: Private | F63: North Island portfolio; institutional wallets | G63: Startup hiring | H63: Via NIV web | I63: - | J63: Monitor | K63: R
A64: Bakkt | B64: Infra (restructured) | C64: Alpharetta, GA | D64: - | E64: Public (BKKT) | F64: Sold loyalty; crypto pivot-and-shrink; DTR/stablecoin pivot attempts | G64: Unstable | H64: - | I64: - | J64: Exclude | K64: K | L64: Avoid: strategy churn
A65: Galaxy Digital | B65: Full platform | C65: New York, NY | D65: HQ | E65: Public (GLXY) | F65: Helios datacenter pivot; Bitstamp + Aplo sell-side mandates (IB); GalaxyOne prime | G65: Corp dev + strategy across arms | H65: One relationship, many doors | I65: Your #1 asymmetric bet (see IB + VC lanes) | J65: S1 | K65: R | L65: Cross-listed on IB Targets
A66: FalconX | B66: Prime broker | C66: San Mateo, CA | D66: Office (verify) | E66: Private | F66: Arbelos buy (2025); 21Shares acquisition agreed (Oct 2025, verify close); serial | G66: Real corp dev; prime growth | H66: Postings + network | I66: PRIME BROKERAGE: your exact COR PRIME world + 21Shares = your ETP world | J66: S1 | K66: K | L66: Promoted to Corp Dev Targets tab; On working tab
A67: Hidden Road (Ripple Prime) | B67: Prime broker | C67: NYC / London | D67: Office | E67: Ripple-owned | F67: $1.25B Ripple buy (2025); now Ripple Prime | G67: Via Ripple lane | H67: Via Ripple postings | I67: Prime brokerage core thesis | J67: S2 | K67: R | L67: In Deal Evidence tab
A68: B2C2 | B68: Market maker / OTC | C68: London, UK | D68: Office (verify) | E68: SBI-owned | F68: SBI-owned liquidity provider | G68: London institutional | H68: London network | I68: Counterparty-type familiarity | J68: S3 | K68: K
A69: Cumberland (DRW) | B69: Trading | C69: Chicago, IL | D69: Office (via DRW NYC) | E69: Private (DRW) | F69: OTC liquidity arm of DRW | G69: Trading-firm hiring | H69: - | I69: - | J69: S3 | K69: K
A70: Wintermute | B70: Market maker | C70: London, UK | D70: Office (opened ~2025, verify) | E70: Private | F70: Dominant algorithmic MM; OTC growth; NYC expansion (verify) | G70: London/NYC trading hiring | H70: Network | I70: Market-structure fluency | J70: S3 | K70: K
A71: GSR | B71: Market maker | C71: London / Singapore | D71: Office (verify) | E71: Private | F71: MM + ventures arm | G71: - | H71: - | I71: - | J71: S3 | K71: K
A72: Flowdesk | B72: Market maker | C72: Paris, FR | D72: Office (verify) | E72: Private | F72: Raised 2024-25; MM-as-a-service | G72: Paris/NYC | H72: - | I72: - | J72: Monitor | K72: K
A73: Keyrock | B73: Market maker | C73: Brussels, BE | D73: - | E73: Private | F73: Acquired Turing Capital (2025, verify); options push | G73: - | H73: - | I73: - | J73: Monitor | K73: K
A74: Amber Group | B74: Trading / wealth | C74: Singapore / HK | D74: - | E74: Public (AMBR via SPAC, verify) | F74: WhaleFin era; restructured | G74: - | H74: - | I74: - | J74: Monitor | K74: K
A75: StoneX Digital | B75: Broker / FCM | C75: New York, NY | D75: HQ | E75: Public (SNEX) | F75: FCM with digital asset desk; acquisitive parent | G75: TradFi hiring | H75: NYC TradFi door | I75: - | J75: Monitor | K75: K
A76: Marex | B76: Broker / FCM | C76: London, UK | D76: Office | E76: Public (MRX) | F76: Digital assets desk build-out (verify) | G76: London hiring | H76: London network | I76: - | J76: Monitor | K76: K
A77: TP ICAP (Fusion Digital Assets) | B77: Interdealer broker | C77: London, UK | D77: Office | E77: Public (TCAP.L) | F77: Fusion Digital Assets venue | G77: London market-structure roles | H77: London network | I77: Interdealer market structure | J77: Monitor | K77: K
A78: Virtu Financial | B78: Market maker | C78: New York, NY | D78: HQ | E78: Public (VIRT) | F78: Crypto MM; EDX backer | G78: NYC trading | H78: - | I78: - | J78: Monitor | K78: K
A79: Citadel Securities | B79: Market maker | C79: Miami, FL | D79: Office (NYC floor) | E79: Private | F79: EDX backer; crypto MM expansion reported (verify) | G79: Elite trading hiring | H79: - | I79: - | J79: Monitor | K79: K
A80: EDX Markets | B80: Exchange (institutional) | C80: Jersey City, NJ | D80: Metro (Jersey City) | E80: Private (consortium) | F80: Schwab/Citadel/Fidelity-backed non-custodial exchange | G80: Small | H80: Network | I80: Market-structure pure play | J80: S3 | K80: K
A81: Chainalysis | B81: Analytics / compliance | C81: New York, NY | D81: HQ | E81: Private | F81: Serial buyer: Hexagate, Alterya (2024-25) | G81: Real corp dev; NYC; MBA-plausible | H81: Postings + NYC network | I81: Egan (Archetype) backed it early | J81: S2 | K81: K | L81: On working tab
A82: TRM Labs | B82: Analytics / compliance | C82: San Francisco, CA | D82: People (verify) | E82: Private | F82: Chainalysis rival; steady raises | G82: Growing | H82: Postings | I82: - | J82: S3 | K82: K
A83: Elliptic | B83: Analytics / compliance | C83: London, UK | D83: Office (verify) | E83: Private | F83: Compliance analytics | G83: London | H83: London network | I83: - | J83: S3 | K83: K
A84: Kaiko | B84: Market data | C84: Paris / NYC | D84: Office | E84: Private | F84: Bought Vinter (index provider, 2024) | G84: Data hiring | H84: Network | I84: INDEX/ETP overlap with your ETC years | J84: S3 | K84: K
A85: Nansen | B85: Analytics | C85: Singapore | D85: - | E85: Private | F85: On-chain analytics; acquisitions (verify) | G85: - | H85: - | I85: - | J85: Monitor | K85: K
A86: Messari | B86: Research / data | C86: New York, NY | D86: HQ | E86: Private | F86: Acquisitive era passed (verify state) | G86: NYC | H86: Network | I86: Galaxy balance-sheet portfolio | J86: Monitor | K86: K
A87: Arkham | B87: Intelligence / exchange | C87: New York, NY | D87: HQ (verify) | E87: Private | F87: Intel platform + exchange | G87: - | H87: - | I87: - | J87: Monitor | K87: K
A88: CCData / CryptoCompare | B88: Market data | C88: London, UK | D88: - | E88: Private | F88: Benchmark/index data | G88: London | H88: - | I88: ETP index adjacency | J88: Monitor | K88: K
A89: BlackRock (Digital Assets) | B89: Asset manager | C89: New York, NY | D89: HQ | E89: Public (BLK) | F89: IBIT juggernaut; BUIDL tokenized fund; Securitize stake | G89: Structured MBA recruiting; digital assets team | H89: Classic MBA door; NYC | I89: Tokenization + ETF = both your theses | J89: S1 | K89: K | L89: On working tab
A90: Fidelity Digital Assets | B90: Asset manager / custody | C90: Boston, MA | D90: Office | E90: Private | F90: FBTC; institutional custody; EDX backer | G90: Structured hiring | H90: Boston/NYC door | I90: - | J90: S2 | K90: K
A91: Grayscale | B91: Asset manager | C91: Stamford, CT | D91: Metro (Stamford) | E91: DCG (IPO filed 2025, verify) | F91: ETF conversions; product expansion | G91: Metro-area | H91: Postings | I91: DCG web | J91: S3 | K91: K
A92: Bitwise | B92: Asset manager | C92: San Francisco, CA | D92: Verify | E92: Private | F92: Bought ETC Group (2024) - YOUR deal; ETF/ETP family | G92: Growing AM hiring | H92: Direct: you are literally alumni-adjacent | I92: They bought your company: warmest cold-call in the set | J92: S1 | K92: K | L92: ETC Group deal in Deal Evidence tab
A93: 21Shares | B93: ETP issuer | C93: Zurich / NYC | D93: Office (US base NYC) | E93: FalconX deal agreed (verify close) | F93: Largest crypto ETP issuer; FalconX acquisition announced Oct 2025 | G93: In transition | H93: Via FalconX web | I93: Direct ETC Group competitor - you know this market cold | J93: S2 | K93: K | L93: On working tab
A94: CoinShares | B94: Asset manager | C94: Jersey / London | D94: Office (verify) | E94: Public (CS.ST) | F94: Bought Valkyrie US ETFs (2024); serial consolidator | G94: London/US hiring | H94: London network | I94: European ETP world = your home turf | J94: S2 | K94: K
A95: WisdomTree | B95: Asset manager | C95: New York, NY | D95: HQ | E95: Public (WT) | F95: Crypto ETFs + WisdomTree Prime tokenized platform | G95: NYC; structured hiring | H95: NYC door | I95: Tokenized funds thesis | J95: S3 | K95: K
A96: VanEck | B96: Asset manager | C96: New York, NY | D96: HQ | E96: Private | F96: Crypto ETFs; Ventures arm (see VC lane) | G96: NYC; lean team | H96: Via VanEck Ventures relationship | I96: ETP background lands here twice | J96: S2 | K96: R | L96: Cross-listed with VC lane
A97: Franklin Templeton | B97: Asset manager | C97: San Mateo, CA | D97: Office | E97: Public (BEN) | F97: BENJI tokenized money fund; crypto ETFs | G97: Structured AM hiring | H97: AM door | I97: Tokenization pioneer among incumbents | J97: S3 | K97: K
A98: ProShares | B98: ETF issuer | C98: Bethesda, MD | D98: - | E98: Private | F98: Futures-based crypto ETFs | G98: - | H98: - | I98: - | J98: Monitor | K98: K
A99: Ark Invest | B99: Asset manager | C99: St. Petersburg, FL | D99: - | E99: Private | F99: Crypto ETFs (with 21Shares); research | G99: Small | H99: - | I99: 21Shares partnership web | J99: Monitor | K99: K
A100: Hashdex | B100: Asset manager | C100: Rio de Janeiro, BR | D100: Office (verify) | E100: Private | F100: Brazil crypto ETF leader; US products | G100: Small; Brazil + NYC | H100: Network | I100: BRAZIL: crypto ETFs in your home market | J100: S2 | K100: K
A101: Galaxy Asset Management | B101: Asset manager | C101: New York, NY | D101: HQ | E101: Public (GLXY) | F101: ETFs (with Invesco), funds | G101: Via Galaxy relationship | H101: Same Galaxy door | I101: - | J101: S2 | K101: R | L101: Cross-listed
A102: Securitize | B102: Tokenization | C102: Miami, FL | D102: Office (verify) | E102: Public (SECZ) | F102: BUIDL issuer for BlackRock; de-SPAC via Cantor (2026) | G102: Growing; public company now | H102: Postings | I102: Tokenized funds = thesis center | J102: S2 | K102: R | L102: In Deal Evidence tab
...

Sheet VC Targets
A1: Venture / VC Targets
A2: Verified against the Aug 2026 NYC fund research | Databases: VC Fund Database (NYC detail) + VC Universe (global) | CVF opens ~Aug 28
A3: Fill in the yellow columns (F to M). | H3: Targets: | I3: =COUNTA($A$6:$A$32) -> 27 | J3: High priority: | K3: =COUNTIF($F$6:$F$32,"High") -> 0 | L3: In motion: | M3: =COUNTA($G$6:$G$32)-COUNTIF($G$6:$G$32,"Not started")-COUNTIF($G$6:$G$32,"Pass") -> 0
A5: Fund | B5: Type | C5: Crypto / Deal Evidence | D5: Hiring Model | E5: Access Channel | F5: Priority | G5: Status | H5: Contact(s) | I5: Contact Source | J5: Last Contact | K5: Next Step | L5: Next Step Date | M5: Notes
A6: Galaxy Ventures | B6: One-roof | C6: Fund I $175M+ (Jun 2025); stablecoins, payments, tokenization; leads Will Nuelle and Mike Giampapa | D6: Small team; platform hires | E6: Same relationship as Galaxy IB; CVF-compatible
A7: Fintech Collective | B7: Fintech VC | C7: ~$500M AUM; the single best stablecoins/payments thesis fit in NYC; capital markets DNA | D7: Small team; seed/A checks $500K-4M | E7: Newsletter, Layer One podcast, Stablecon conference
A8: Archetype | B8: Independent | C8: Fund III $100M+ (Sep 2025); stablecoins, payments infra, crypto x AI; Ash Egan, Katherine Wu | D8: Concentrated team; occasional roles | E8: Archebyte podcast, NYC in-person events
A9: Variant | B9: Independent | C9: Variant 4 $222M (Jun 2026); crypto x AI 'autonomy' thesis; Jesse Walden, Li Jin; Brooklyn | D9: Small team | E9: Thesis essays; writing-first outreach works here
A10: CoinFund | B10: Independent | C10: $550M+ raised across recent vehicles; Brooklyn RIA; venture plus liquid; market-structure focus | D10: Small team; has hired early-career | E10: NYC events plus CVF; research and podcast engagement
A11: Portal Ventures | B11: Independent | C11: Fund II $75M (late 2024); pre-seed lead checks; fundamentals-driven; Evan Fisher (ex-Insight) | D11: Small; hires early-career | E11: Fisher's writing and podcasts; MBA-friendly framing
A12: VanEck Ventures | B12: Corporate fund | C12: $30M debut fund (Oct 2024); ex-Circle Ventures team (Lonergan, Lopez); stablecoin/tokenization thesis | D12: Tiny team; accessible | E12: Media-active partners; direct outreach viable
A13: 6th Man Ventures | B13: Independent | C13: Fund II $145M; consumer and Solana-weighted; Mike Dudas (The Block co-founder), Serge Kassardjian | D13: Small team | E13: Dudas is highly public; NYC events
A14: North Island Ventures | B14: Independent | C14: ~$300M AUM; Travis Scher (ex-DCG), Glenn Hutchins; stablecoin payments and interoperability thesis | D14: Small; has advertised associate roles | E14: Scher podcasts; watch for openings
A15: Dragonfly (NYC) | B15: Bicoastal | C15: Fund IV $650M (Feb 2026); RWA and stablecoin pivot; ~$4B AUM; note DOJ/Tornado Cash caveat on one GP | D15: Small NYC bench; occasional roles | E15: Chopping Block podcast, research
A16: Union Square Ventures | B16: Independent | C16: Thesis-driven; early Coinbase backer; still leading crypto rounds in 2025 | D16: Small; has run analyst and fellow programs | E16: CVF plus thoughtful written outreach; they reward writing
A17: Castle Island Ventures | B17: Independent | C17: Backed both Talos and Coin Metrics; Boston HQ (not NYC); founders Nic Carter, Matt Walsh | D17: Small partnership; occasional fellows | E17: Post-close Talos angle; engage On The Brink first
... A32: Index Ventures | B32: Generalist w/ crypto | C32: NYC office; backed Bridge (sold to Stripe, $1.1B) - a live stablecoin credential; deep fintech bench | D32: Structured associate hiring exists; competitive | E32: NYC office network; fintech partners; verify current crypto appetite
A34: Keep this lane in quiet channels during the EB cycle: CVF, Galaxy and Broadhaven relationships, and CVC coffees. Never signal the venture endgame in Tier 1 IB conversations. Non-NYC entries (Castle Island, Pantera, Kraken/Coinbase Ventures) are kept for relationship reasons; the full NYC universe is on the VC Fund Database tab. Rows 21-30 added Aug 22, 2026 from general knowledge (Jan 2026 horizon), not the verified research - verify before citing. Global fund universe on the VC Universe tab. Rows 31-32 (a16z crypto, Index Ventures) added for NYC-office reachability.

Sheet VC Fund Database
A1: NYC Crypto VC Fund Database: Full Detail (verified Aug 2026)
A2: Every fund from the Aug 22, 2026 deep research at full fidelity: complete fund lineages, founders, LPs, and 2025-26 deal activity | Sections: NYC crypto-native, bicoastal, generalists, corporate/metro, excluded
A4: Fund | B4: HQ / Main Location | C4: NYC Presence | D4: Status | E4: Founded | F4: Founders & Key People | G4: Fund History (all vehicles) | H4: Strategy & Checks | I4: Thesis / Focus | J4: Portfolio | K4: Recent Activity 2025-26 | L4: LPs / Backers | M4: Engagement Hooks | N4: Priority | O4: Notes / Caveats
A5: CoinFund | B5: Brooklyn, NY | C5: HQ | D5: Active | E5: 2015 | F5: Jake Brukhman (Managing Partner/CEO), Aleksandr Bulkin (co-founder), Alex Felix (Managing Partner/CIO); registered investment adviser | G5: $550M+ raised over 18 months across vehicles: $158M early-stage fund (2023, above its $125M target); Ventures I $300M (2022, Series A focus); Seed IV; deploying from Fund III and other vehicles in 2025-26 | H5: Pre-seed through growth; equity + liquid tokens; network lifecycle investing approach | I5: DeFi, infrastructure, AI agents, market structure, stablecoins/payments | J5: Solana, Polygon, Dapper Labs, Blockdaemon | K5: Recent deals: Veda, Dakota, Ether.fi, Irys, Kadena, Trace Finance, Pluralis | L5: Not disclosed | M5: Active research and publishing, partner podcasts, regulatory engagement, careers page | N5: S1 | O5: RIA registration is an institutional-credibility marker in this set
A6: Archetype | B6: New York, NY | C6: HQ | D6: Active | E6: 2021 | F6: Ash Egan (Founder/GP; co-launched ConsenSys Ventures, ex-Accomplice); Katherine Wu (ex-Coinbase Ventures) | G6: $55M debut fund (2021); Fund II $155M (2022); Fund III $100M+ total commitments (Sep 2025); ~$350M reported assets | H6: Concentrated, high-conviction first check to Series A; equity + liquid positions (holds Solana and Ethereum) | I6: Onchain social, stablecoins, payments infrastructure, modular stacks, crypto x AI, DePIN | J6: Privy (acquired by Stripe), Rated, US Bitcoin Corp; Egan backed Chainalysis pre-Archetype | K6: Fund III close Sep 2025 | L6: Pensions, endowments, sovereign wealth funds, funds of funds, family offices | M6: Archebyte podcast, NYC in-person events, content platform | N6: S1 | O6: Egan frames the deliberately small Fund III as buying extreme selectivity and conviction per team
A7: Variant | B7: Brooklyn, NY (1027 Grand St) | C7: HQ | D7: Active | E7: 2020 | F7: Jesse Walden (ex-a16z crypto); Li Jin (co-GP; her Atelier Ventures merged in) | G7: $22.5M (2020); $110M (2021); Fund III $450M total, split $150M seed + $300M opportunity (2022); Variant 4 $222M (Jun 2026) | H7: Pre-seed/seed; equity + tokens | I7: Ownership economy; Variant 4 reframed around autonomy (crypto x AI) | J7: Uniswap, Phantom, Magic Eden, Mirror, Zora, Foundation, Flashbots, Blockaid | K7: Variant 4 close Jun 2026 | L7: Not disclosed | M7: Heavy research and writing cadence; thesis essays | N7: S1 | O7: Walden's view: within four years crypto investor will be as generic a label as internet investor
A8: Galaxy Ventures | B8: New York, NY | C8: HQ | D8: Active | E8: Fund I 2024-25; platform investing since 2018 | F8: Will Nuelle and Mike Giampapa (fund leads); affiliate of Galaxy (Nasdaq: GLXY; Mike Novogratz) | G8: Fund I $175M+ final close (Jun 2025), above its $150M target; first external venture capital after 120+ balance-sheet investments since 2018 | H8: Early-stage equity plus co-investment; ~30 companies; $3-5M checks | I8: Stablecoins, payments, tokenization, and supporting infrastructure | J8: Ethena, Monad, Plume, 1Money, DoubleZero, Citrea, Arch Lending; balance-sheet legacy: Pyth, Chaos Labs, Fireblocks, Messari | K8: Deploying Fund I | L8: Institutional investors, family offices, fund-of-funds, strategic corporates (names undisclosed) | M8: Galaxy Research; platform team; ~550-person institutional footprint | N8: S1 | O8: Exits include Tagomi and Bison Trails, both to Coinbase; Novogratz cast the above-target close in a hard market as proof of edge
A9: 6th Man Ventures | B9: New York, NY | C9: HQ | D9: Active | E9: 2021 | F9: Mike Dudas (co-founder of The Block), Serge Kassardjian | G9: Fund II $145M (~2022) | H9: Pre-seed to Series A; equity + tokens; checks up to $4-5M; roughly one deal per month; ~50% Solana-weighted | I9: Consumer crypto, apps, infrastructure, gaming, media | J9: Magic Eden, io.net, Livepeer, Pump.fun | K9: Recent: Veera, worm.wtf, Inversion | L9: LPs included Galaxy Vision Hill; Marc Andreessen, Chris Dixon, and Bill Ackman invested personally | M9: Dudas is highly public on X; Breakpoint keynotes | N9: S1
A10: Placeholder | B10: New York, NY | C10: HQ | D10: Active (slower) | E10: 2017 | F10: Chris Burniske, Joel Monegro (both ex-USV lineage); Brad Burnham (venture partner); Mario Laul (research) | G10: ~$150M managed | H10: Venture + public-market liquid hybrid; long-hold; 75+ investments | I10: Thesis-driven protocol investing | J10: Ethereum, Solana, Celestia, Monad, Aleo, Eclipse, Backpack, Squads, Tensor, Jito | K10: 1-2 new deals per year recently | L10: Not disclosed | M10: Extensive public research library; partner podcasts; Burniske's cryptoasset valuation frameworks | N10: S2 | O10: Iconic thesis shop; deployment pace is the tradeoff
A11: Hivemind Capital | B11: New York, NY | C11: HQ | D11: Active (hybrid) | E11: 2021 | F11: Matt Zhang (ex-Citi head of structured products trading); Richard Skeet (London; co-lead, runs the liquid platform) | G11: Launched with a $1.5B multi-strategy mandate (venture, liquid staking/yield, trading, play-to-earn gaming); Liquid Opportunity Fund $300M target (2023); Digital Culture Fund ~$50M target (2024, digital art) | H11: Hybrid venture + liquid + trading; real venture sleeve | I11: Multi-strategy digital assets | J11: Varied | L11: Not disclosed | M11: Institutional profile; less founder-facing | N11: S3 | O11: NYC HQ but liquid investing reports to London
A12: Blockchange Ventures | B12: New York, NY | C12: HQ | D12: Active | E12: Fall 2017 | F12: Ken Seiff (MP; ex-Bluefly, Beanstalk Ventures); Caroline Kassie; Dr. Gavin Wood (part-time GP); Rob Schmults (GP); Janice Chan (CFO); Jon Freedman (COO/CLO) | G12: Multiple funds across the Fund I to IV era | H12: Early-stage; equity + tokens | I12: Base layers and L1s | J12: Solana, Polkadot, Near, Flow, Dapper Labs, Figure, Axelar, Arbitrum, Zama | K12: ~62 active positions; 7 new investments in the trailing 12 months as of mid-2026 | L12: Not disclosed | M12: Seiff accessible via podcasts (The Defiant) | N12: S2 | O12: Gavin Wood's part-time GP role is an unusual signal
A13: North Island Ventures | B13: New York, NY | C13: HQ | D13: Active | E13: 2020 | F13: Travis Scher (ex-DCG VP of investments), James Hutchins (ex-Coatue research), Glenn Hutchins (Silver Lake co-founder; Chairman) | G13: Fund I ~$72M debut; Fund II $125M (2022); ~$300M AUM | H13: Early-stage; $250K-3M initial checks; 30-40 companies per fund; equity + tokens | I13: Interoperability (network of networks), DeFi, stablecoin payments, onchain neobanking | J13: Axelar, BCB Group, Dapper Labs, Flow, Immunefi, Polymer, Figure, Ether.fi, Utila | L13: Not disclosed | M13: Scher is public via podcasts and X; the firm has advertised associate hiring | N13: S2 | O13: The associate-hiring history makes this a live seat to watch, not just a coffee
A14: Portal Ventures | B14: New York, NY | C14: HQ | D14: Active | E14: 2022 | F14: Evan Fisher (ex-Insight Partners, ex-Goldman; Forbes 30 Under 30; Michigan Ross BBA '17); Catrina Wang (GP) | G14: Fund I $35-40M (2022); Fund II $75M closed late 2024, oversubscribed against ~$90M of interest | H14: Pre-seed lead investor; equity + tokens | I14: Fundamentals-driven protocol and business-model thesis; current theme: crypto rails for latent markets | J14: Uranium Digital | K14: Fund II deploying | L14: Backers include Chris Dixon and Marc Andreessen personally, and KKR's Henry Kravis | M14: Fisher's writing and podcasts; hires early-career | N14: S1 | O14: The most MBA-legible investment framing in the NYC set
A15: Reciprocal Ventures | B15: New York, NY (24 W 25th St) | C15: HQ | D15: Active (raising III) | E15: 2016 | F15: Michael Steinberg (ex-SAC/Point72 PM); Craig Burel (GP) | G15: Fund II $68.5M (2022); Fund III raising up to $100M, in market from early 2025; ~$201M AUM | H15: Pre-seed/seed; equity + tokens | I15: DeFi, institutional capital markets, web3 stack, payments | J15: Solana (seed), The Graph, TrueX, Coinflow Labs | K15: Fund III in market | L15: Not disclosed | M15: Diffusion thesis research; partner writing | N15: S2
A16: M31 Capital | B16: New York, NY | C16: HQ | D16: Active (liquid-heavy) | E16: 2020 | F16: Nathan Montone; offices in Scottsdale, SF, Shanghai, Seoul, Delhi, San Juan | G16: ~$100M Web3 Opportunity Fund (Oct 2022, liquid venture); Bitcoin fund; DeFi fund; M31 Ventures arm | H16: Multi-strategy; venture arm invests equity + tokens | I16: Broad web3 | J16: Huddle01, Euler, Elsa | K16: Latest venture deal: Euler (Jul 2025) | L16: Not disclosed | M16: Modest venture cadence | N16: S3 | O16: Hybrid and liquid-heavy; venture is a sleeve
A17: Dragonfly | B17: NYC + Singapore (legal HQ Oakland/SF per some filings) | C17: Major office | D17: Active | E17: 2018 | F17: Founded by Alex Pack and Bo Feng; Haseeb Qureshi (Managing Partner); GPs Rob Hadick, Tom Schmidt | G17: Fund IV $650M (Feb 2026), 30% above its $500M target, matching Fund III (2022); ~$4B total AUM; acquired Metastable, one of the oldest crypto hedge funds | H17: Seed through Series B+; $3-30M checks; equity + liquid | I17: 2025-26 pivot toward financial infrastructure, stablecoins, real-world assets, onchain finance | J17: Polymarket, Ethena, Rain, Mesh, Avalanche, Agora | K17: Fund IV close Feb 2026 | L17: Not disclosed | M17: The Chopping Block podcast; research | N17: S1 | O17: Caveat: DOJ signaled possible charges in 2025 tied to a 2020 Tornado Cash investment involving GP Tom Schmidt; Qureshi noted the raise landed amid deep bear-market gloom
A18: a16z crypto | B18: Menlo Park HQ; NYC office | C18: Office | D18: Active | E18: 2018 | F18: Chris Dixon (founder/lead; Columbia BA and MA in philosophy, HBS MBA); GPs Ali Yahya, Guy Wuollet, Eddy Lazzarin (newly promoted) | G18: Crypto Fund 5 $2.2B (May 2026); $9.8B total crypto capital | H18: Seed to growth; $10-60M checks; equity + tokens | I18: Fund 5 targets stablecoins, tokenization, perpetual futures, prediction markets, and AI agents; deep CLARITY Act and GENIUS Act policy engagement | J18: Coinbase, Uniswap, OpenSea, Solana | K18: Crypto Fund 5 close May 2026 | L18: Not disclosed | M18: Crypto Startup School accelerator; a16z crypto research; State of Crypto report; active recruiting | N18: S2 | O18: Highly competitive; the Dixon Columbia tie is a legitimate hook
A19: 1kx | B19: Berlin (some databases list New York) | C19: Partners only | D19: Active | E19: 2017-18 | F19: Lasse Clausen, Christopher Heymann | G19: $75M fund closed Mar 2024 | H19: Seed/A; token-network specialist; equity + tokens | I19: Token networks | J19: Celestia, Arweave, Solana, Reown/WalletConnect, LI.FI, Layer3 | L19: Not disclosed | N19: Monitor | O19: Should not be counted as an NYC fund in practice
A20: Lightspeed Faction | B20: Menlo Park / SF | C20: No | D20: Active | E20: 2023 | F20: Sam Harrison, Banafsheh Fathieh | G20: $285M inaugural fund (2023) | H20: Early-stage crypto | L20: Lightspeed-affiliated | N20: Exclude | O20: West Coast; on the map only to close the question of whether it belongs here
A21: Union Square Ventures | B21: New York, NY | C21: HQ | D21: Active | E21: 2003-04 | F21: Fred Wilson, Brad Burnham (founders) | G21: Last core fund $275M plus $350M opportunity fund (2022, $625M total); small funds by design | H21: Series A-centric equity; collaborative decision-making | I21: Thesis 3.0; crypto since 2013 (first bet Coinbase); 25+ web3 positions | J21: Coinbase, Uniswap, Polygon, Helium, Dapper | K21: Led a 2025 prediction-market startup round alongside Coinbase Ventures | L21: Not disclosed | M21: USV thesis blog; Fred Wilson's AVC; alumni lineage runs to Placeholder (Monegro, Burniske era) | N21: S1 | O21: They reward writing; written outreach plays to this
A22: Fintech Collective | B22: New York, NY (200 Park Ave S) | C22: HQ | D22: Active | E22: 2012 | F22: Brooks Gibbins, Gareth Jones | G22: ~$500M AUM; 7 funds; 171 investments; 14 exits | H22: Seed/A; $500K-4M checks; equity | I22: Fintech + DeFi crossover; stablecoins, payments, capital markets DNA | J22: 171 investments (individual crypto names not detailed in the research) | L22: Not disclosed | M22: Newsletters (The Dollar's New Avatar; Stablecoins Take the Lead); Layer One podcast; adjacent to the Stablecon NYC conference | N22: S1 | O22: Best pure stablecoins/payments thesis fit in the city
A23: RRE Ventures | B23: New York, NY (130 E 59th) | C23: HQ | D23: Active | E23: 1994 | F23: Long-standing NYC partnership | G23: ~$2.5B AUM; 5 funds | H23: Seed/A; primarily equity | I23: Generalist with a dedicated crypto focus area | J23: Ripple, Paxos, Binance.US, BitPay, Blockdaemon, Abra, Bitnomial | K23: Active in 2025-26 | L23: Not disclosed | M23: NYC generalist brand; crypto focus page | N23: S2 | O23: Bitnomial overlap connects to your Deal Evidence tab
A24: Insight Partners | B24: New York, NY | C24: HQ | D24: Active (crypto episodic) | E24: Growth platform | G24: ~$90B AUM | H24: Growth equity | I24: Crypto-adjacent since 2020 | J24: FTX (historic), TaxBit | L24: Not disclosed | M24: Portal's Evan Fisher is an alumnus | N24: S3 | O24: Crypto is opportunistic, not a practice
A25: Thrive Capital | B25: New York, NY (Puck Building) | C25: HQ | D25: Active (minimal crypto) | E25: 2009 | F25: Josh Kushner | G25: Thrive X $10B (Feb 2026); ~$50-65B AUM | H25: Growth; equity | I25: AI, consumer, enterprise core; crypto peripheral | J25: OpenAI, Stripe, SpaceX; Robinhood on the historic fintech side | L25: Not disclosed | N25: Monitor | O25: Peripheral for this thesis
A26: Deviation Capital (ex-Two Sigma Ventures) | B26: New York, NY | C26: HQ | D26: Active (crypto sleeve) | E26: Rebranded 2025-26 | G26: ~$400M across two 2022 funds; roughly 15% allocated to crypto/web3 | H26: Data-driven generalist; equity | I26: Crypto is a minority sleeve | J26: Pyth, Omni, Rally | L26: Not disclosed | N26: S3 | O26: Verify the rebrand on the firm's site before outreach
A27: Valor Capital Group | B27: New York, NY (+ Rio, Sao Paulo) | C27: HQ | D27: Active (crypto opportunistic) | E27: 2011 | F27: Sobel family | G27: ~$2.2B AUM | H27: US-Brazil/LatAm crossover; equity | I27: Crypto limited and opportunistic | J27: Coinbase, Bitso, Valora | L27: Not disclosed | N27: S2 | O27: Personal edge: your Sao Paulo M&A years and dual citizenship are differentiated here
A28: VanEck Ventures | B28: New York, NY (666 Third Ave) | C28: HQ | D28: Active | E28: Oct 2024 | F28: Wyatt Lonergan, Juan Lopez (both ex-Circle Ventures) | G28: $30M debut fund closed early 2025; related PurposeBuilt Fund launched Jun 2025 (liquid + venture) | H28: Pre-seed/seed; $500K-1M checks; 25-35 companies; equity | I28: Fintech + digital assets + AI; stablecoins and tokenization | J28: Building portfolio | K28: Actively deploying | L28: VanEck (parent) | M28: Media-active partners; direct outreach viable | N28: S1 | O28: The Circle Ventures spinout story is the natural intro line
A29: Circle Ventures | B29: New York, NY (One World Trade Center) | C29: HQ | D29: Active (modest) | E29: CVC | F29: Circle relocated HQ around its Jun 2025 NYSE IPO (CRCL, ~$1.05B raised) | G29: ~9 investments to date | H29: CVC equity | I29: USDC ecosystem | J29: Latest: Zodia Markets (Jul 2025) | L29: Circle (parent) | N29: S3 | O29: Prior VC leads left to found VanEck Ventures, thinning dedicated activity
A30: Consensys / Mesh | B30: Brooklyn, NY | C30: HQ | D30: Active (slower) | E30: Consensys 2014; Mesh 2015, independent 2020 | F30: Joe Lubin (founder) | G30: ~138 equity/token positions; Tachyon and TachyonX accelerators (90+ projects) | H30: CVC equity + tokens; accelerator | I30: Ethereum ecosystem | J30: MetaMask, Gnosis, Aztec, Gitcoin | K30: Mesh new-deal cadence below peak | M30: Tachyon accelerator; ecosystem events | N30: S2 | O30: Consensys IPO delayed to fall 2026 after the Feb 2026 downturn; ARR $150M+; last valued $7B (2022)
A31: Ava Labs / Blizzard Fund | B31: Brooklyn, NY (+ Miami) | C31: HQ | D31: Active | E31: 2018 | F31: Emin Gun Sirer, Kevin Sekniqi, Ted Yin | G31: Ava Labs raised $250M in Dec 2024 (Galaxy-led); Blizzard is a $200M+ Avalanche ecosystem fund (launched 2021) | H31: Ecosystem equity + tokens | I31: Avalanche ecosystem | J31: 150+ Blizzard investments | K31: Still deploying into the ecosystem | L31: Galaxy led the Dec 2024 raise | M31: Ecosystem events | N31: S2
A32: Winklevoss Capital / Gemini | B32: New York, NY (30 W 24th) | C32: HQ | D32: Active | E32: 2012 | F32: Cameron and Tyler Winklevoss | G32: ~172 investments; 24 exits | H32: Family office VC; equity + BTC | I32: Crypto, space, energy, biotech | J32: Broad portfolio | K32: Gemini Space Station (Nasdaq: GEMI) IPO priced at $28, above the $24-26 range, Sep 2025; 15,178,572 Class A shares; ~$425M raised at ~$3.3B valuation; reported 20x oversubscribed; Nasdaq committed a $50M private placement | N32: S3 | O32: Gemini stock later fell sharply; Winklevoss Capital injected $100M at $14/share in May 2026, paid in bitcoin
A33: Republic Capital / Crypto | B33: New York, NY | C33: HQ | D33: Active | E33: Republic 2016; Capital arm 2019 | F33: Organized as Republic Capital (multi-stage VC), Republic Digital (crypto hedge fund), Republic Crypto (advisory) | G33: $2.6B+ deployed across 2,500+ ventures | H33: Multi-stage; equity + tokens | I33: Tokenized assets and retail platform push in 2026 | J33: Broad | K33: Latest Republic Capital deal: Neblio Technologies (Oct 2025) | L33: Backed by Galaxy, Binance, Naspers | M33: Platform events | N33: S2
A34: White Star Capital DAF | B34: New York (DAF team; global firm: London, Paris, Montreal, Toronto, Tokyo, Singapore) | C34: Team | D34: Active (modest cadence) | E34: DAF I 2021 | F34: Sep Alavi (Managing Partner); Eddie Lee, Luke Xiao (DAF team) | G34: DAF I $50M (2021); DAF II $120M first close (2022, Ubisoft anchor) | H34: Seed/A; equity + tokens | I34: DeFi, gaming | J34: Ledn, RedStone, Etherfuse, Kulipa | K34: Latest: Alfred (Jan 2026) | L34: Ubisoft anchored DAF II | N34: S3
A35: DCG | B35: Stamford, CT (relocated from Manhattan 2021) | C35: Metro | D35: Active | E35: 2015 | F35: Barry Silbert | G35: 200+ investments; targeting a $1B Fund V per PitchBook | H35: CVC/operator; venture equity + private tokens + event-driven plays | I35: Broad digital assets | J35: Grayscale, Foundry, Luno | M35: Metro-area coffee range | N35: S3 | O35: Genesis went bankrupt in 2023; CoinDesk was sold
A36: 50T (ex-10T / 1RT) | B36: Stamford/Greenwich, CT | C36: Metro | D36: Active | E36: 10T 2021; 1RT 2023; merged as 50T Jul 2025 | F36: Dan Tapiero | G36: $500M growth-equity fund launched at the merger; ~$2B combined AUM | H36: Growth equity; no tokens | I36: Growth-stage digital assets | J36: Kraken, Yuga Labs, Animoca, Ledger, Ledn, Quicknode | N36: S3 | O36: Growth-stage crossover angle only
A37: Bitkraft Ventures | B37: Denver/Berlin (NYC is one of several offices) | C37: Office | D37: Active | F37: Jens Hilgers (founder); Carlos Pereira leads web3 | G37: $1B+ AUM; Fund III $275M (2024) plus token funds | H37: Web3 gaming; equity + tokens | I37: Gaming and interactive media | J37: Gaming portfolio | N37: Monitor | O37: Gaming-only relevance
A38: Metalayer | B38: NYC-linked (verify HQ) | C38: Verify | D38: Active (emerging) | E38: Recent | F38: Founded by Two Sigma veterans | G38: ~$25M fund | H38: Early-stage crypto | J38: The research associates the fund with Ethena and Clear Token; verify whether as backers or portfolio | N38: Monitor | O38: Newly surfaced in the research; small but worth tracking as an emerging vehicle
A39: Neoclassic Capital | B39: Miami, FL | C39: NYC-connected | D39: Active | E39: 2024 | F39: Michael Bucella (ex-BlockTower), Steve Lee | H39: Early-stage crypto | I39: Broad | J39: Building | L39: Backers include Marc Andreessen and Chris Dixon personally | M39: Bucella is NYC-visible and media-active | N39: Monitor | O39: The firm is Miami despite the NYC network
A40: Breed VC | B40: Boston/Miami roots (databases list Boston/NY) | C40: Listings vary | D40: Active (small) | F40: Jed Breed | G40: Fund I $20M (2023); Fund II first close ~$13.6M (Nov 2025) | H40: Small early-stage | J40: Small portfolio | L40: Fund I backed by Castle Island's Nic Carter and Matt Walsh, Tribe Capital, Shima Capital | N40: Monitor | O40: The Castle Island connection ties into your Talos web
A41: Syncracy Capital | B41: New York, NY | C41: HQ | D41: Not venture (liquid) | F41: Ryan Watkins, Daniel Cheung | G41: ~$230M AUM | H41: Liquid token hedge fund | N41: Exclude | O41: Exclude from VC targeting; the research output is still worth reading
A42: Brevan Howard Digital | B42: UK / Austin | C42: No | D42: Mostly liquid | G42: Fund fell 29.5% in 2025, its worst year since launch, driven by illiquid markdowns | H42: Liquid with a minority venture sleeve | I42: Shifting toward stablecoins and infrastructure | N42: Exclude | O42: Not an NYC venture target
A43: NYDIG / Stone Ridge | B43: New York, NY | C43: HQ | D43: Not VC | F43: Ross Stevens | H43: Bitcoin financial services: custody, mining, power | K43: Acquired Crusoe's bitcoin mining operations (Mar 2025) | N43: Exclude | O43: Interesting company, wrong lane for VC targeting
A44: ProCap (Pompliano) | B44: New York, NY | C44: HQ | D44: Not VC | F44: Anthony Pompliano | G44: $750M+ raised; SPAC merger completed Dec 2025 (Nasdaq: BRR, via Columbus Circle Capital Corp I) | H44: Bitcoin treasury company | K44: Shares fell sharply post-merger amid the broader derating of 2025-vintage bitcoin treasury companies | N44: Exclude
A45: Tusk Venture Partners | B45: New York, NY | C45: HQ | D45: Winding down VC | F45: Bradley Tusk, Jordan Nof | G45: Fund III (2022) announced as the last traditional venture fund | H45: Pivoting to an equity-for-services regulatory consulting model | I45: Regulatory-adjacent crypto historically | J45: Coinbase, Circle, Ripple (regulatory-adjacent) | N45: Exclude | O45: Do not spend networking time here
A46: Point72 Ventures | B46: Stamford parent | C46: No | D46: Exited crypto VC | H46: Now AI, defense, enterprise | K46: Crypto and digital assets team laid off Jun 2024 | N46: Exclude | O46: No active crypto VC
A48: Full-fidelity transfer of the Aug 22, 2026 deep research: complete fund lineages, founder rosters, LP compositions, and 2025-26 activity as reported. Blank cells mean the research did not surface that field, not that it does not exist. Fund sizes from third-party databases are approximate; confirm final closes with each firm before citing in conversation.

Sheet VC Universe
A1: VC Universe
A2: The global crypto-fund universe with NYC reachability | 149 funds | Filter the NYC Presence column to plan coffee-chat range
A3: Src: R = verified Aug 2026 research; K = general knowledge - VERIFY. NYC Presence: HQ / Metro (commutable) / Office / Team / People (individuals based there) / Verify (unconfirmed) / '-' none known. K-confidence, Jan 2026 horizon - confirm before planning outreach around it. Yellow column O is yours. | K3: Entries: | L3: =COUNTA($A$6:$A$154) -> 149
A5: Fund | B5: HQ | C5: NYC Presence | D5: Region | E5: Type | F5: Scale (approx) | G5: Stage & Instruments | H5: Thesis / Focus | I5: Key People | J5: Portfolio / Evidence | K5: MBA Door | L5: Priority | M5: Src | N5: Notes | O5: Your Flag
A6: CoinFund | B6: Brooklyn, NY | C6: HQ | D6: NYC | E6: Crypto-native VC | F6: $550M+ recent vehicles | G6: Pre-seed to growth; equity + liquid | H6: Market structure, stablecoins, DeFi, AI agents | I6: Jake Brukhman, Alex Felix | J6: Solana, Polygon, Dapper; recent: Veda, Ether.fi | K6: Has hired early-career; NYC events + CVF | L6: S1 | M6: R | N6: Full detail on VC Fund Database tab; On working tab
A7: Archetype | B7: New York, NY | C7: HQ | D7: NYC | E7: Crypto-native VC | F7: Fund III $100M+ (2025) | G7: First check to Series A; equity + liquid | H7: Stablecoins, payments infra, crypto x AI, DePIN | I7: Ash Egan, Katherine Wu | J7: Privy (-> Stripe), Rated | K7: Archebyte podcast; NYC events | L7: S1 | M7: R | N7: Full detail on VC Fund Database tab; On working tab
A8: Variant | B8: Brooklyn, NY | C8: HQ | D8: NYC | E8: Crypto-native VC | F8: Variant 4 $222M (2026) | G8: Pre-seed/seed; equity + tokens | H8: Ownership economy; autonomy (crypto x AI) | I8: Jesse Walden, Li Jin | J8: Uniswap, Phantom, Magic Eden, Flashbots | K8: Writing-first outreach | L8: S1 | M8: R | N8: Full detail on VC Fund Database tab; On working tab
A9: Galaxy Ventures | B9: New York, NY | C9: HQ | D9: NYC | E9: One-roof platform | F9: Fund I $175M+ (2025) | G9: Early-stage equity; $3-5M checks | H9: Stablecoins, payments, tokenization | I9: Will Nuelle, Mike Giampapa | J9: Ethena, Monad, Plume, Fireblocks (b/s) | K9: Platform hires; CVF-compatible | L9: S1 | M9: R | N9: Full detail on VC Fund Database tab; On working tab
A10: 6th Man Ventures | B10: New York, NY | C10: HQ | D10: NYC | E10: Crypto-native VC | F10: Fund II $145M | G10: Pre-seed to A; equity + tokens | H10: Consumer, Solana, gaming, media | I10: Mike Dudas, Serge Kassardjian | J10: Magic Eden, io.net, Pump.fun | K10: Dudas highly public; NYC events | L10: S1 | M10: R | N10: Full detail on VC Fund Database tab; On working tab
A11: Placeholder | B11: New York, NY | C11: HQ | D11: NYC | E11: Crypto-native hybrid | F11: ~$150M | G11: Long-hold venture + liquid | H11: Thesis-driven protocols | I11: Chris Burniske, Joel Monegro | J11: Ethereum, Solana, Celestia, Monad | K11: Research library; slower cadence | L11: S2 | M11: R | N11: Full detail on VC Fund Database tab
A12: Hivemind Capital | B12: New York, NY | C12: HQ | D12: NYC | E12: Multi-strategy hybrid | F12: $1.5B launch mandate | G12: Venture sleeve + liquid + trading | H12: Multi-strategy digital assets | I12: Matt Zhang | J12: Varied | K12: Institutional; less founder-facing | L12: S3 | M12: R | N12: Full detail on VC Fund Database tab
A13: Blockchange Ventures | B13: New York, NY | C13: HQ | D13: NYC | E13: Crypto-native VC | F13: Funds I-IV | G13: Early-stage; equity + tokens | H13: Base layers / L1s | I13: Ken Seiff | J13: Solana, Polkadot, Near, Arbitrum | K13: Seiff podcast-accessible | L13: S2 | M13: R | N13: Full detail on VC Fund Database tab
A14: North Island Ventures | B14: New York, NY | C14: HQ | D14: NYC | E14: Crypto-native VC | F14: ~$300M AUM | G14: Early-stage; $250K-3M checks | H14: Stablecoin payments, interoperability, DeFi | I14: Travis Scher, Glenn Hutchins | J14: Axelar, Flow, Ether.fi, Utila | K14: Has advertised associate roles | L14: S2 | M14: R | N14: Full detail on VC Fund Database tab; On working tab
A15: Portal Ventures | B15: New York, NY | C15: HQ | D15: NYC | E15: Crypto-native VC | F15: Fund II $75M (2024) | G15: Pre-seed lead; equity + tokens | H15: Fundamentals-driven; crypto rails | I15: Evan Fisher, Catrina Wang | J15: Uranium Digital | K15: Hires early-career; MBA-legible | L15: S1 | M15: R | N15: Full detail on VC Fund Database tab; On working tab
A16: Reciprocal Ventures | B16: New York, NY | C16: HQ | D16: NYC | E16: Crypto-native VC | F16: Fund III raising ~$100M | G16: Pre-seed/seed; equity + tokens | H16: DeFi, institutional capital markets, payments | I16: Michael Steinberg, Craig Burel | J16: Solana (seed), The Graph | K16: Diffusion-thesis research | L16: S2 | M16: R | N16: Full detail on VC Fund Database tab
A17: M31 Capital | B17: New York, NY | C17: HQ | D17: NYC | E17: Multi-strategy hybrid | F17: ~$100M Web3 fund | G17: Venture sleeve; liquid-heavy | H17: Broad web3 | I17: Nathan Montone | J17: Huddle01, Euler | K17: Modest cadence | L17: S3 | M17: R | N17: Full detail on VC Fund Database tab
... A72: Slow Ventures | B72: SF / Boston / NYC | C72: People (verify) | D72: US West | E72: Generalist w/ crypto sleeve | F72: n/a | G72: Seed | H72: Contrarian consumer + crypto | I72: Sam Lessin | J72: Solana (early), social bets | K72: Essay culture | L72: S3 | M72: K | N72: Crypto is a sleeve
A73: Volt Capital | B73: San Francisco, CA | C73: - | D73: US West | E73: Crypto-native VC (small) | F73: $50M (2022, verify) | G73: Seed | H73: Infra, DeFi | I73: Soona Amhaz | J73: Seed portfolio | K73: Small; community-led | L73: S3 | M73: K
A74: Chapter One | B74: Los Angeles, CA | C74: - | D74: US West | E74: Product-led seed | F74: n/a | G74: Seed | H74: Consumer crypto + product | I74: Jeff Morris Jr. | J74: Consumer bets | K74: Product angle | L74: S3 | M74: K
A75: Shima Capital | B75: San Francisco, CA | C75: - | D75: US West | E75: Crypto-native seed | F75: $200M Fund I (2022) | G75: High-volume seed | H75: Broad web3 | I75: Yida Gao | J75: Large seed portfolio | K75: Volume player | L75: S3 | M75: K | N75: Verify current pace
A76: Tribe Capital | B76: San Jose, CA | C76: - | D76: US West | E76: Data-driven VC w/ crypto | F76: n/a | G76: Multi-stage | H76: Data-driven; crypto sleeve | I76: Arjun Sethi (also Kraken co-CEO) | J76: Kraken (large position) | K76: Kraken web overlap | L76: S3 | M76: K | N76: Sethi bridge to Kraken
A77: Race Capital | B77: San Francisco, CA | C77: - | D77: US West | E77: Infra-focused seed | F77: n/a | G77: Seed | H77: Infra, data, crypto-adjacent | I77: Alfred Chuang | J77: Solana (early) | K77: Infra angle | L77: S3 | M77: K
A78: gumi Cryptos Capital (gCC) | B78: SF + Tokyo | C78: - | D78: US West | E78: Crypto-native VC | F78: ~$150M+ funds (verify) | G78: Seed | H78: Infra, DeFi, Japan bridge | I78: Miko Matsumura | J78: Broad seed | K78: Japan angle | L78: S3 | M78: K
A79: Boost VC | B79: San Mateo, CA | C79: - | D79: US West | E79: Accelerator + seed | F79: n/a | G79: Pre-seed accelerator | H79: Sci-fi tech incl. crypto | I79: Adam Draper | J79: Long crypto history (2014+) | K79: Accelerator network | L79: Monitor | M79: K
A80: Draper Associates | B80: San Mateo, CA | C80: - | D80: US West | E80: Family of funds | F80: n/a | G80: Seed | H80: Bitcoin-forward | I80: Tim Draper | J80: Coinbase (early), bitcoin bets | K80: Brand only | L80: Monitor | M80: K
A81: Arrington Capital | B81: Seattle, WA | C81: - | D81: US Other | E81: Crypto-native VC + liquid | F81: n/a | G81: Venture + liquid | H81: L1s, infra | I81: Michael Arrington, Ninor Mansor | J81: Broad | K81: - | L81: Monitor | M81: K
A82: Bloccelerate VC | B82: Seattle, WA | C82: - | D82: US Other | E82: Crypto-native VC (small) | F82: n/a | G82: Seed | H82: Infra | I82: Kate Mitselmakher | J82: - | K82: - | L82: Monitor | M82: K
A83: Arca | B83: Los Angeles, CA | C83: - | D83: US West | E83: Asset manager + venture | F83: n/a | G83: Liquid + venture sleeve | H83: Digital assets, funds | I83: Rayne Steinberg, Jeff Dorman | J83: - | K83: Research notes are useful | L83: Monitor | M83: K | N83: Liquid-leaning
A84: Ribbit Capital | B84: Menlo Park, CA | C84: - | D84: US West | E84: Fintech elite w/ crypto | F84: Multi-$B | G84: Seed to growth equity | H84: Global fintech; crypto conviction cycles | I84: Micky Malka | J84: Coinbase, Robinhood, Nubank, Revolut | K84: Elite fintech door; MBA-plausible | L84: S2 | M84: K | N84: Fintech-crypto crossover royalty; On working tab
A85: Founders Fund | B85: San Francisco, CA | C85: Verify | D85: US West | E85: Generalist w/ BTC conviction | F85: Multi-$B | G85: Multi-stage equity | H85: Contrarian; bitcoin, Polymarket | I85: Peter Thiel; team | J85: Polymarket, bitcoin positions | K85: Elite; network entry | L85: S3 | M85: K
A86: Sequoia Capital | B86: Menlo Park, CA | C86: Office (opened ~2024, verify) | D86: US West | E86: Generalist mega-fund | F86: Multi-$B | G86: Multi-stage equity | H86: Selective crypto (post-FTX chastened) | I86: - | J86: Fireblocks, Polygon (verify), FTX (writedown) | K86: Elite generalist door | L86: S3 | M86: K | N86: Crypto selective
A87: Index Ventures | B87: SF + London | C87: Office | D87: US West | E87: Generalist w/ crypto bets | F87: Multi-$B | G87: Multi-stage equity | H87: Selective crypto/fintech | I87: - | J87: Bridge (-> Stripe), fintech heavy | K87: Elite generalist door | L87: S3 | M87: K | N87: On working tab
A88: General Catalyst | B88: SF + NYC | C88: Office | D88: US West | E88: Generalist mega-fund | F88: Multi-$B | G88: Multi-stage | H88: Fintech + selective crypto | I88: - | J88: Circle (early backer, verify) | K88: Large MBA-friendly platform | L88: S3 | M88: K
A89: Khosla Ventures | B89: Menlo Park, CA | C89: - | D89: US West | E89: Generalist w/ crypto bets | F89: Multi-$B | G89: Multi-stage | H89: Deep tech; selective crypto/stablecoin | I89: - | J89: OpenSea (verify), stablecoin bets | K89: - | L89: Monitor | M89: K
A90: GV (Google Ventures) | B90: Mountain View, CA | C90: Office | D90: US West | E90: CVC generalist | F90: Multi-$B | G90: Multi-stage | H90: Selective crypto infra | I90: - | J90: Dapper, Blockchain.com (verify) | K90: - | L90: Monitor | M90: K
A91: 8VC | B91: Austin, TX | C91: Office (verify) | D91: US Other | E91: Generalist w/ crypto-adjacent | F91: Multi-$B | G91: Multi-stage | H91: Fintech infra, defense; stablecoin-curious | I91: Joe Lonsdale | J91: Synthetic-dollar adjacency (verify) | K91: - | L91: Monitor | M91: K
A92: Coatue | B92: New York, NY | C92: HQ | D92: NYC | E92: Crossover w/ crypto history | F92: Multi-$B | G92: Growth + liquid | H92: AI core; crypto episodic | I92: - | J92: OpenSea era bets | K92: - | L92: Monitor | M92: K
A93: CMT Digital | B93: Chicago, IL | C93: - | D93: US Other | E93: Trading-family crypto VC | F93: n/a | G93: Early-stage equity + tokens | H93: Market structure, infra, policy | I93: CMT Group lineage | J93: Long crypto-native portfolio | K93: Market-structure DNA; strong thesis fit | L93: S2 | M93: K | N93: Trading-firm capital speaks your language
A94: DRW Venture Capital | B94: Chicago, IL | C94: Office (via DRW NYC) | D94: US Other | E94: Prop-firm VC (Cumberland) | F94: n/a | G94: Equity | H94: Market infra, digital assets | I94: DRW/Cumberland lineage | J94: ErisX (historic), infra bets | K94: Cumberland adjacency | L94: S3 | M94: K
A95: Jump Capital / Jump Crypto | B95: Chicago, IL | C95: Office (via Jump NYC) | D95: US Other | E95: Prop-firm VC + builder | F95: n/a | G95: Equity + tokens + building | H95: Infra, DeFi, Solana ecosystem | I95: - | J95: Pyth ecosystem, Wormhole (rebuilt) | K95: Engineering-heavy | L95: S3 | M95: K | N95: Post-2022 rebuild; verify current posture
A96: Greenfield Capital | B96: Berlin, DE | C96: - | D96: Europe | E96: Crypto-native VC | F96: EUR 160M Fund III (verify) | G96: Seed/A; equity + tokens | H96: Open-source infra, ETH-aligned | I96: Sebastian Blum, Jascha Samadi | J96: Infra portfolio | K96: Leading German crypto fund | L96: Monitor | M96: K | N96: Europe network relevance
A97: Fabric Ventures | B97: London, UK | C97: - | D97: Europe | E97: Crypto-native VC | F97: ~$245M (2022, verify) | G97: Seed; equity + tokens | H97: Open economy, infra | I97: Richard Muirhead | J97: Polkadot-era to present | K97: London network fits your base | L97: S3 | M97: K
A98: Outlier Ventures | B98: London, UK | C98: - | D98: Europe | E98: Accelerator | F98: n/a | G98: Pre-seed accelerator | H98: Web3 broad | I98: Jamie Burke | J98: Large accelerator cohort history | K98: Mentor network | L98: Monitor | M98: K
A99: CoinShares Ventures | B99: London / Jersey | C99: Office (verify) | D99: Europe | E99: Corporate VC | F99: n/a | G99: Equity | H99: Digital asset infra | I99: CoinShares (listed) | J99: ETP-adjacent bets | K99: ETP-house overlap with your ETC years | L99: S3 | M99: K
A100: KR1 | B100: Isle of Man / UK | C100: - | D100: Europe | E100: Listed crypto investor | F100: Listed vehicle | G100: Tokens + equity | H100: Staking, protocols | I100: - | J100: Long protocol list | K100: - | L100: Monitor | M100: K
A101: L1 Digital (L1D) | B101: Zurich, CH | C101: - | D101: Europe | E101: Fund-of-funds + direct | F101: ~$1B+ AUM (verify) | G101: FoF + co-invest | H101: Crypto funds universe | I101: Ray Hindi | J101: - | K101: Knows every fund: meta-networking | L101: S3 | M101: K | N101: A FoF conversation maps the whole industry
A102: CV VC | B102: Zug, CH | C102: - | D102: Europe | E102: Crypto-native VC + accelerator | F102: n/a | G102: Seed | H102: Crypto Valley ecosystem | I102: Mathias Ruch | J102: - | K102: - | L102: Monitor | M102: K
A103: Signature Ventures | B103: Munich, DE | C103: - | D103: Europe | E103: Crypto-native VC (small) | F103: n/a | G103: Seed | H103: Infra | I103: - | J103: - | K103: - | L103: Monitor | M103: K
A104: Maven 11 | B104: Amsterdam, NL | C104: - | D104: Europe | E104: Crypto-native VC | F104: ~$120M+ funds (verify) | G104: Seed/A; equity + tokens | H104: DeFi, infra, credit | I104: - | J104: Maple, credit protocols (verify) | K104: Lending-protocol thesis overlap | L104: S3 | M104: K
A105: Rockaway Blockchain Fund (RBF) | B105: Prague, CZ | C105: - | D105: Europe | E105: Crypto-native VC | F105: n/a | G105: Seed/A | H105: Infra, DeFi | I105: Viktor Fischer | J105: - | K105: - | L105: Monitor | M105: K
A106: Lightshift | B106: Lisbon, PT | C106: - | D106: Europe | E106: Crypto-native VC (small) | F106: n/a | G106: Seed + studio | H106: Infra | I106: - | J106: - | K106: - | L106: Monitor | M106: K
A107: Blue Yard Capital | B107: Berlin, DE | C107: - | D107: Europe | E107: Thesis-driven seed | F107: n/a | G107: Seed | H107: Decentralization, frontier | I107: Ciaran O'Leary | J107: Protocol bets | K107: - | L107: Monitor | M107: K
A108: Hashed | B108: Seoul, KR | C108: - | D108: Asia | E108: Crypto-native VC | F108: ~$570M across funds (verify) | G108: Seed to A; equity + tokens | H108: Korea + global web3, gaming | I108: Simon Kim | J108: Korean ecosystem + global bets | K108: Korea bridge | L108: Monitor | M108: K
A109: HashKey Capital | B109: Hong Kong | C109: People (verify) | D109: Asia | E109: Crypto-native VC + platform | F109: ~$1B AUM (verify) | G109: Multi-stage; equity + tokens | H109: Asia institutional crypto | I109: Deng Chao | J109: Broad Asia portfolio | K109: HK licensing regime knowledge | L109: Monitor | M109: K
A110: Animoca Brands | B110: Hong Kong | C110: - | D110: Asia | E110: Operator + investor | F110: 400+ investments | G110: Equity + tokens | H110: Gaming, metaverse-era, consumer | I110: Yat Siu | J110: Sandbox, gaming universe | K110: Gaming only | L110: Monitor | M110: K
A111: Spartan Group | B111: Singapore | C111: - | D111: Asia | E111: Crypto-native VC + advisory | F111: n/a | G111: Venture + advisory + liquid | H111: DeFi, gaming, infra | I111: Kelvin Koh | J111: DeFi portfolio | K111: Advisory arm does crypto M&A - watch | L111: S3 | M111: K | N111: Their advisory practice overlaps your IB lane
A112: Foresight Ventures | B112: Singapore | C112: - | D112: Asia | E112: Crypto-native VC | F112: n/a | G112: Seed/A | H112: Infra, Asia-US bridge | I112: - | J112: The Block (majority owner!) | K112: Media asset connection | L112: Monitor | M112: K | N112: Owns The Block - Dudas history
A113: IOSG Ventures | B113: Singapore / Shenzhen | C113: - | D113: Asia | E113: Crypto-native VC | F113: n/a | G113: Seed; research-driven | H113: Infra, ZK, DeFi | I113: Jocy Lin | J113: Infra-heavy portfolio | K113: - | L113: Monitor | M113: K
A114: SevenX Ventures | B114: Asia (distributed) | C114: - | D114: Asia | E114: Crypto-native VC | F114: n/a | G114: Seed | H114: Infra, consumer | I114: - | J114: - | K114: - | L114: Monitor | M114: K
A115: Fenbushi Capital | B115: Shanghai / Singapore | C115: - | D115: Asia | E115: Crypto-native VC (oldest Asia) | F115: n/a | G115: Equity + tokens | H115: Blockchain broad | I115: Bo Shen | J115: Ethereum-era history | K115: - | L115: Monitor | M115: K
A116: Ryze Labs (ex-Sino Global) | B116: Asia / distributed | C116: Office (verify) | D116: Asia | E116: Crypto-native VC | F116: n/a | G116: Seed | H116: Solana-aligned, Asia | I116: - | J116: Solana ecosystem | K116: - | L116: Monitor | M116: K
A117: Mirana Ventures | B117: Singapore / Dubai | C117: - | D117: Asia | E117: CVC (Bybit-affiliated) | F117: n/a | G117: Equity + tokens | H117: Exchange ecosystem | I117: - | J117: - | K117: - | L117: Monitor | M117: K
A118: OKX Ventures | B118: Hong Kong / Seychelles | C118: - | D118: Asia | E118: CVC | F118: n/a | G118: Equity + tokens | H118: Exchange ecosystem | I118: - | J118: Broad | K118: - | L118: Monitor | M118: K
A119: YZi Labs (ex-Binance Labs) | B119: Global | C119: - | D119: Asia | E119: CVC / incubator | F119: $10B era portfolio (verify) | G119: Equity + tokens + incubation | H119: BNB ecosystem + broad | I119: Ella Zhang era relaunch (verify) | J119: Massive portfolio | K119: US practicality low | L119: Monitor | M119: K | N119: Rebranded from Binance Labs 2025
A120: SBI Investment | B120: Tokyo, JP | C120: - | D120: Asia | E120: CVC (SBI Group) | F120: Multi-fund | G120: Equity | H120: Japan digital assets | I120: - | J120: B2C2, bitbank (group deals) | K120: Group's bitbank/B2C2 M&A = corp dev overlap | L120: Monitor | M120: K
A121: Sora Ventures | B121: Taipei, TW | C121: - | D121: Asia | E121: Crypto-native VC (small) | F121: n/a | G121: Seed | H121: Bitcoin DATs in Asia, media | I121: Jason Fang | J121: Asia DAT deals | K121: - | L121: Monitor | M121: K
A122: Hashed Emergent | B122: Bangalore, IN | C122: - | D122: Asia | E122: Crypto-native VC | F122: n/a | G122: Seed | H122: India web3 | I122: - | J122: - | K122: - | L122: Monitor | M122: K
A123: Superscrypt | B123: Singapore | C123: - | D123: Asia | E123: Temasek-linked crypto VC | F123: n/a | G123: Seed | H123: Infra, consumer | I123: - | J123: - | K123: Institutional Singapore angle | L123: Monitor | M123: K
A124: Further Ventures | B124: Abu Dhabi, UAE | C124: - | D124: MEA | E124: ADQ-backed VC + studio | F124: n/a | G124: Venture + build | H124: Digital assets, fintech market infra | I124: - | J124: Stablecoin/market-infra bets | K124: ADGM regime; capital-rich | L124: Monitor | M124: K | N124: Gulf capital increasingly active in your thesis area
A125: Cypher Capital | B125: Dubai, UAE | C125: - | D125: MEA | E125: Crypto-native VC | F125: n/a | G125: Seed | H125: Broad web3 | I125: - | J125: - | K125: - | L125: Monitor | M125: K
A126: Apollo Crypto | B126: Melbourne, AU | C126: - | D126: Oceania | E126: Crypto-native VC + liquid | F126: n/a | G126: Venture + liquid | H126: Broad | I126: - | J126: - | K126: - | L126: Monitor | M126: K
A127: Tether Investments | B127: El Salvador | C127: - | D127: Global | E127: Strategic investor (CVC-like) | F127: $B-scale profits deployed | G127: Large strategic checks | H127: AI, energy, bitcoin mining, media, agriculture | I127: Paolo Ardoino | J127: Adecoagro (~70%), Twenty One, Rumble (verify) | K127: Not a hiring door; strategic weight only | L127: Monitor | M127: K | N127: The most capital-rich strategic in crypto
A128: RippleX / Ripple investments | B128: San Francisco, CA | C128: Office (via Ripple NYC) | D128: US West | E128: CVC / ecosystem | F128: n/a | G128: Equity + XRPL grants | H128: XRPL ecosystem, payments | I128: - | J128: Ecosystem grants + corp dev overlap | K128: Enter via Ripple corp dev lane | L128: S3 | M128: K | N128: Double-counts with Corp Dev tab
A129: Stellar Development Foundation | B129: San Francisco, CA | C129: - | D129: US West | E129: Ecosystem fund | F129: Enterprise Fund | G129: Equity + grants | H129: Payments, anchors, MoneyGram web | I129: Denelle Dixon | J129: MoneyGram partnership era | K129: Payments thesis adjacency | L129: Monitor | M129: K
A130: Polygon Ventures | B130: Global / remote | C130: People (verify) | D130: Global | E130: Ecosystem fund | F130: n/a | G130: Equity + tokens | H130: Polygon ecosystem | I130: - | J130: Coinme buy (Polygon Labs corp dev) | K130: Ecosystem door | L130: Monitor | M130: K
A131: Aptos (ecosystem investing) | B131: Palo Alto, CA | C131: - | D131: US West | E131: Ecosystem fund | F131: n/a | G131: Equity + tokens | H131: Aptos ecosystem | I131: Avery Ching | J131: - | K131: - | L131: Monitor | M131: K
A132: CME Ventures | B132: Chicago, IL | C132: Office | D132: US Other | E132: Exchange CVC | F132: n/a | G132: Equity | H132: Market infrastructure | I132: - | J132: Digital-asset infra bets | K132: TradFi market-structure door | L132: S3 | M132: K
A133: Nasdaq Ventures | B133: New York, NY | C133: HQ | D133: NYC | E133: Exchange CVC | F133: n/a | G133: Equity | H133: Market tech, digital assets | I133: - | J133: Gemini placement ($50M, 2025 IPO) | K133: NYC TradFi door | L133: S3 | M133: K
A134: ICE / NYSE strategic | B134: Atlanta / NYC | C134: HQ (NYSE) | D134: US Other | E134: Exchange strategic | F134: n/a | G134: Strategic stakes | H134: Market infra; prediction markets | I134: - | J134: Bakkt; Polymarket stake (2025, verify) | K134: - | L134: S3 | M134: K | N134: Polymarket bet signals conviction
A135: Visa Ventures | B135: San Francisco, CA | C135: Office (verify) | D135: US West | E135: Payments CVC | F135: n/a | G135: Equity | H135: Stablecoin settlement, payments infra | I135: Cuy Sheffield (crypto lead) | J135: Stablecoin infra bets | K135: Visa crypto team hires; MBA-friendly parent | L135: S2 | M135: K | N135: On Corp Dev working tab as Visa
A136: PayPal Ventures | B136: San Jose, CA | C136: Office (Venmo NYC) | D136: US West | E136: Payments CVC | F136: n/a | G136: Equity | H136: Fintech, stablecoin ecosystem (PYUSD) | I136: - | J136: Stablecoin/payments bets | K136: MBA-friendly parent | L136: S2 | M136: K | N136: On Corp Dev working tab as PayPal
A137: Amex Ventures | B137: New York, NY | C137: HQ | D137: NYC | E137: Payments CVC | F137: n/a | G137: Equity | H137: Fintech; selective crypto | I137: - | J137: - | K137: NYC; MBA-friendly parent | L137: S3 | M137: K
A138: Citi Ventures | B138: New York, NY | C138: HQ | D138: NYC | E138: Bank CVC | F138: n/a | G138: Equity | H138: Fintech; tokenization-curious | I138: - | J138: - | K138: Bank platform door | L138: S3 | M138: K
A139: SC Ventures (Standard Chartered) | B139: Singapore / London | C139: - | D139: Europe | E139: Bank venture builder | F139: n/a | G139: Build + invest | H139: Digital assets ventures | I139: - | J139: Built Zodia Custody & Zodia Markets | K139: Venture-building model worth studying | L139: S3 | M139: K | N139: Zodia web connects to Deal Evidence
A140: Goldman Sachs (strategic/growth) | B140: New York, NY | C140: HQ | D140: NYC | E140: Bank strategic investor | F140: n/a | G140: Growth equity | H140: Market infra, digital assets | I140: - | J140: Coin Metrics, Anchorage (verify rounds) | K140: GS platform door; TradFi lane | L140: S3 | M140: K
A141: Laser Digital (Nomura) | B141: London / Dubai | C141: Verify | D141: Europe | E141: Bank-owned digital assets | F141: n/a | G141: Venture + trading | H141: Digital asset infra | I141: Jez Mohideen | J141: Infra bets | K141: TradFi-crypto bridge employer | L141: S3 | M141: K
A142: Samsung Next | B142: San Francisco, CA | C142: Office (verify) | D142: US West | E142: CVC | F142: n/a | G142: Seed equity | H142: Frontier tech incl. web3 | I142: - | J142: Web3 seed bets | K142: - | L142: Monitor | M142: K
A143: Franklin Templeton (digital assets) | B143: San Mateo, CA | C143: Office | D143: US West | E143: Asset-manager strategic | F143: n/a | G143: Fund investments + strategic | H143: Tokenization (BENJI), funds | I143: Roger Bayston (verify) | J143: On-chain money fund pioneer | K143: Asset-mgmt door; tokenization thesis | L143: S3 | M143: K
A144: Alliance DAO | B144: Remote / NYC events | C144: Events/cohorts in NYC | D144: Global | E144: Crypto accelerator | F144: n/a | G144: Pre-seed accelerator | H144: Top crypto accelerator | I144: Qiao Wang, Imran Khan | J144: Strong founder network | K144: Their demo days = deal flow map | L144: S3 | M144: K | N144: Watching their cohorts = seeing next year's deals
A145: Colosseum | B145: Remote / global | C145: - | D145: Global | E145: Solana accelerator + fund | F145: n/a | G145: Hackathon-to-fund | H145: Solana ecosystem | I145: Matty Taylor | J145: Solana startup pipeline | K145: Pairs with 6MV Solana weighting | L145: Monitor | M145: K
A146: Orange DAO | B146: Remote | C146: - | D146: Global | E146: YC-alumni crypto fund | F146: n/a | G146: Pre-seed | H146: YC-network crypto founders | I146: - | J146: - | K146: - | L146: Monitor | M146: K
A147: a16z Crypto Startup School (CSX) | B147: NYC + SF | C147: Cohorts in NYC | D147: NYC | E147: Accelerator | F147: Cohort-based | G147: Accelerator + checks | H147: Crypto startups | I147: - | J147: Cohort network | K147: NYC cohorts; recruiting surface | L147: S3 | M147: K | N147: Also an a16z relationship surface
A148: Maelstrom | B148: Hong Kong | C148: - | D148: Asia | E148: Family office (Arthur Hayes) | F148: n/a | G148: Liquid + seed | H148: DeFi, infra | I148: Arthur Hayes | J148: - | K148: Essays widely read; not a hiring door | L148: Exclude | M148: K | N148: Context/reading only
A149: Nascent | B149: Remote / US | C149: People (verify) | D149: Global | E149: Liquid + venture hybrid | F149: n/a | G149: Liquid-first | H149: DeFi | I149: Dan Elitzer | J149: - | K149: Not a hiring door | L149: Exclude | M149: K | N149: Context only
A150: QED Investors | B150: Alexandria, VA | C150: Verify | D150: US Other | E150: Fintech specialist VC | F150: Multi-$B | G150: Seed to growth equity | H150: Global fintech; stablecoin-curious | I150: Nigel Morris | J150: LatAm fintech depth (Nubank etc.) | K150: MBA-friendly; LatAm overlap | L150: S2 | M150: K | N150: Brazil fintech web overlaps your background
A151: Bain Capital Ventures (fintech) | B151: Boston + NYC + SF | C151: Office | D151: US Other | E151: Generalist w/ fintech depth | F151: Multi-$B | G151: Multi-stage equity | H151: Fintech infra; stablecoin bets | I151: - | J151: Fintech infra portfolio | K151: MBA-friendly platform | L151: S3 | M151: K | N151: Distinct from Bain Capital Crypto
A152: Fin Capital | B152: San Francisco, CA | C152: Verify | D152: US West | E152: Fintech VC | F152: n/a | G152: Multi-stage | H152: B2B fintech; digital assets sleeve | I152: Logan Allin | J152: - | K152: - | L152: Monitor | M152: K
A153: Clocktower Technology Ventures | B153: Santa Monica, CA | C153: - | D153: US West | E153: Macro-fintech VC | F153: n/a | G153: Seed/A | H153: Fintech; LatAm program | I153: Ben Savage | J153: LatAm fintech | K153: LatAm angle | L153: Monitor | M153: K
A154: Propel Venture Partners | B154: San Francisco, CA | C154: - | D154: US West | E154: Fintech VC (BBVA-seeded) | F154: n/a | G154: Seed/A | H154: Fintech; crypto-adjacent | I154: - | J154: Coinbase (early, verify) | K154: - | L154: Monitor | M154: K
A156: Compiled Aug 22, 2026. Src K rows carry a Jan 2026 information horizon: fund sizes, rosters, NYC-office footprints, and even fund existence MUST be verified before outreach or citation. 'n/a' means not confidently known, not zero. NYC rows are summaries - full verified detail on the VC Fund Database tab. Funds marked 'On working tab' are worked on the VC Targets tab. Priorities: S1 pursue, S2 engage, S3 track, Monitor watch, Exclude avoid.

Sheet People Directory
A1: People Directory: Named Individuals Across All Lanes
A2: Named individuals across all lanes, research + universe expansion | Verify current role on LinkedIn before ANY outreach
A3: Fill in the yellow columns (G to K) as you verify and meet people. | E3: People: | F3: =COUNTA($A$6:$A$89) -> 84
A5: Person | B5: Firm | C5: Role / Background | D5: Lane | E5: Engagement Channel / Hook | F5: Personal or Columbia Tie | G5: LinkedIn (verified) | H5: Status | I5: Last Contact | J5: Next Step | K5: Notes
A6: Will Nuelle | B6: Galaxy Ventures | C6: Fund I co-lead | D6: VC | E6: Galaxy Research; NYC events; CVF | F6: Galaxy is your dual IB + Ventures door
A7: Mike Giampapa | B7: Galaxy Ventures | C7: Fund I co-lead | D7: VC | E7: Galaxy Research; NYC events | F7: -
A8: Mike Novogratz | B8: Galaxy Digital | C8: Founder/CEO (Nasdaq: GLXY) | D8: Context | E8: Public figure; not an outreach target - know his framing of the Fund I raise | F8: -
A9: Jake Brukhman | B9: CoinFund | C9: Co-founder, Managing Partner/CEO (2015) | D9: VC | E9: CoinFund research and podcast; NYC events | F9: Brooklyn proximity: weekly-visible fund
A10: Alex Felix | B10: CoinFund | C10: Managing Partner/CIO | D10: VC | E10: Research engagement | F10: -
A11: Aleksandr Bulkin | B11: CoinFund | C11: Co-founder | D11: VC | F11: -
A12: Ash Egan | B12: Archetype | C12: Founder/GP; co-launched ConsenSys Ventures, ex-Accomplice | D12: VC | E12: Archebyte podcast; Archetype NYC events | F12: -
A13: Katherine Wu | B13: Archetype | C13: Team; ex-Coinbase Ventures | D13: VC | E13: Content platform; NYC events | F13: -
A14: Jesse Walden | B14: Variant | C14: Co-founder; ex-a16z crypto | D14: VC | E14: Thesis essays - respond in writing | F14: -
A15: Li Jin | B15: Variant | C15: Co-GP; merged Atelier Ventures in | D15: VC | E15: Writing on ownership economy | F15: -
A16: Brooks Gibbins | B16: Fintech Collective | C16: Co-founder (2012) | D16: VC | E16: Newsletter; Layer One podcast; Stablecon | F16: Capital-markets DNA matches your prime-lending seat
A17: Gareth Jones | B17: Fintech Collective | C17: Co-founder | D17: VC | E17: Newsletter; Stablecon | F17: -
A18: Evan Fisher | B18: Portal Ventures | C18: Founder; ex-Insight Partners, ex-Goldman; Michigan Ross BBA '17 | D18: VC | E18: His writing and podcasts; fundamentals framing | F18: Most MBA-friendly investor in the set; Insight alumni web
A19: Catrina Wang | B19: Portal Ventures | C19: GP | D19: VC | E19: Portal content | F19: -
A20: Mike Dudas | B20: 6th Man Ventures | C20: Co-founder; co-founded The Block | D20: VC | E20: Highly public on X; Breakpoint keynotes | F20: -
A21: Serge Kassardjian | B21: 6th Man Ventures | C21: Co-founder | D21: VC | E21: NYC events | F21: -
A22: Haseeb Qureshi | B22: Dragonfly | C22: Managing Partner | D22: VC | E22: The Chopping Block podcast; research | F22: -
A23: Rob Hadick | B23: Dragonfly | C23: General Partner | D23: VC | E23: Research; NYC events | F23: -
... A29: Travis Scher | B29: North Island Ventures | C29: Co-founder; ex-DCG VP of investments | D29: VC | E29: Podcasts and X; NIV has advertised associate roles | F29: Watch for a live associate seat
A30: James Hutchins | B30: North Island Ventures | C30: Co-founder; ex-Coatue research | D30: VC | F30: -
A31: Glenn Hutchins | B31: North Island Ventures | C31: Chairman; Silver Lake co-founder | D31: Context | E31: Institutional gravitas; not a cold-outreach target | F31: -
A32: Chris Burniske | B32: Placeholder | C32: Partner; cryptoasset valuation frameworks | D32: VC | E32: Research library; podcasts - his valuation work is CVF-ready material | F32: -
A33: Joel Monegro | B33: Placeholder | C33: Partner; ex-USV (fat protocols thesis) | D33: VC | E33: Research library | F33: -
A34: Mario Laul | B34: Placeholder | C34: Head of research | D34: VC | E34: Research engagement | F34: -
A35: Ken Seiff | B35: Blockchange Ventures | C35: Managing Partner; ex-Bluefly, Beanstalk | D35: VC | E35: Accessible via podcasts (The Defiant) | F35: -
A36: Gavin Wood | B36: Blockchange Ventures | C36: Part-time GP; Polkadot founder | D36: Context | E36: Unusual signal about the firm, not an outreach path | F36: -
A37: Michael Steinberg | B37: Reciprocal Ventures | C37: Founder; ex-SAC/Point72 PM | D37: VC | E37: Diffusion-thesis research; partner writing | F37: Institutional capital-markets thesis fits your background
A38: Craig Burel | B38: Reciprocal Ventures | C38: GP | D38: VC | E38: Partner writing | F38: -
A39: Matt Zhang | B39: Hivemind Capital | C39: Founder; ex-Citi head of structured products trading | D39: VC | E39: Institutional profile | F39: Structured-products lineage speaks your prime-lending language
A40: Chris Dixon | B40: a16z crypto | C40: Founder/lead of the crypto franchise; GP | D40: VC | E40: a16z crypto research; Crypto Startup School; State of Crypto | F40: COLUMBIA: BA and MA in philosophy - the single best alumni hook in the dataset
A41: Ali Yahya | B41: a16z crypto | C41: General Partner | D41: VC | E41: Research and podcast | F41: -
A42: Guy Wuollet | B42: a16z crypto | C42: General Partner | D42: VC | E42: Research | F42: -
... A60: Arjun Sethi | B60: Kraken / Payward | C60: Co-CEO | D60: Corp Dev | E60: Watch strategy hires around the IPO window | F60: -
A61: David Ripley | B61: Kraken / Payward | C61: Co-CEO | D61: Corp Dev | F61: -
A62: Anton Katz | B62: Talos | C62: CEO | D62: Corp Dev | E62: FROZEN: no contact of any kind while Project Optimus is live; warmest door after close | F62: Your counterparty today; your reference tomorrow
A63: Matt Huang | B63: Paradigm | C63: Co-founder/Managing Partner; ex-Sequoia | D63: VC | E63: Paradigm research and writing | F63: -
A64: Fred Ehrsam | B64: Paradigm | C64: Co-founder; Coinbase co-founder; reduced day-to-day role - verify | D64: VC | E64: Writing; public talks | F64: -
A65: Katie Haun | B65: Haun Ventures | C65: Founder/CEO; ex-a16z crypto GP, ex-federal prosecutor | D65: VC | E65: Policy and regulatory events | F65: -
A66: Avichal Garg | B66: Electric Capital | C66: Co-founder; Developer Report franchise | D66: VC | E66: Developer Report engagement | F66: -
A67: Olaf Carlson-Wee | B67: Polychain | C67: Founder/CEO; Coinbase employee #1 | D67: VC | E67: Podcasts | F67: -
A68: Kyle Samani | B68: Multicoin | C68: Co-founder/MP; prolific thesis writer | D68: VC | E68: Multicoin blog; Solana ecosystem | F68: -
A69: Tushar Jain | B69: Multicoin | C69: Co-founder/MP | D69: VC | E69: Multicoin blog | F69: -
A70: Ben Forman | B70: ParaFi Capital | C70: Founder/Managing Partner; ex-KKR | D70: VC | E70: ParaFi research; NYC | F70: KKR-to-crypto arc parallels your TradFi-to-crypto story; NYC proximity
A71: Micky Malka | B71: Ribbit Capital | C71: Founder; fintech-crypto crossover | D71: VC | E71: Warm intros only | F71: -
A72: Hans Morris | B72: Nyca Partners | C72: Managing Partner; ex-president of Visa | D72: VC | E72: NYC fintech network | F72: Payments royalty; Nyca has MBA hiring precedent
A73: Mark Beeston | B73: Illuminate Financial | C73: Founder/Managing Partner; ex-ICAP | D73: VC | E73: Capital-markets fintech events | F73: Market-structure thesis bullseye
... A89: Yuval Rooz | B89: Digital Asset | C89: Co-founder/CEO | D89: Corp Dev | E89: Institutional events; NYC | F89: Canton = post-trade market structure
A91: Limited to publicly prominent, stable figures named in the Aug 2026 research and tracker; roles change fast in this market, so ALWAYS verify on LinkedIn before outreach and log the verified profile in column G. Where a firm has a platform/careers channel, lead with the firm, not the founder. The Talos and Dragonfly caution rows are non-negotiable. Rows 63 onward added Aug 22, 2026 from general knowledge (Jan 2026 horizon) alongside the universe expansion - verify roles before outreach.

Sheet Target Profiles
A1: Target Profiles: Depth per Target
A3: Target | B3: Lane | C3: HQ / Scale | D3: Crypto / Deal Evidence | E3: Hiring Reality | F3: Entry Route & People | G3: Timing | H3: Watch Items
A4: PJT Partners | B4: 1 - OCR | C4: NYC HQ; boutique scale, small associate classes | D4: NinjaTrader (Kraken buy), Bitnomial (sell), Reap (Payward buy); Core Scientific Ch. 11 debtors and co-sell to CoreWeave | E4: Structured summer associate program; RSSG restructuring recruits on a separate, MBA-heavy track | F4: OCR plus IBC closed lists; build 2 to 3 advocates before January | G4: Sept to Jan | H4: Flow concentrates in the Payward relationship; pitch market-structure conviction, not one client. If RSSG appeals, decide early; the tracks split
A5: Evercore | B5: 1 - OCR | C5: NYC HQ; largest associate class among the EBs | D5: Co-lead FA to Siris on the $4.2B Equiniti sale | E5: Structured program; best raw odds in the EB set | F5: Core OCR name; consistent CBS hirer | G5: Sept to Jan | H5: Crypto exposure is episodic; the play is brand plus optionality, not thesis density
A6: Moelis | B6: 1 - OCR | C6: NYC HQ | D6: Voyager, Genesis, BlockFi debtor mandates; Bitfarms buy-side; Core Scientific co-sell | E6: Structured program; restructuring and M&A staffing can cross | F6: Standard OCR process | G6: Sept to Jan | H6: Tied with PJT for most mandates in the dataset; restructuring flow is the counter-cyclical hedge if crypto M&A slows
A7: Centerview | B7: 1 - OCR | C7: NYC HQ; tiny class | D7: Celsius Ch. 11 debtor banker, ~$20M fee allocation | E7: Most selective of the group; generalist staffing | F7: OCR | G7: Sept to Jan | H7: Lowest odds, highest per-seat prestige; crypto is incidental to the platform
A8: Perella Weinberg | B8: 1 - OCR | C8: NYC HQ | D8: FTX debtors banker (ran LedgerX and FTX Europe sales); Celsius creditors | E8: Structured program | F8: OCR | G8: Sept to Jan | H8: Estate work built the crypto muscle; ask how the market-structure franchise carries forward post-FTX
A9: Lazard | B9: 1 - OCR | C9: NYC HQ | D9: Co-FA to FTAI on the $1.5B Long Ridge sale | E9: Structured program | F9: OCR | G9: Sept to Jan | H9: Episodic crypto; portfolio filler only
A10: Houlihan Lokey | B10: 1 - OCR | C10: NYC and LA; restructuring powerhouse | D10: Genesis creditors; creditor-side across the 2022-24 bankruptcies | E10: Structured; corporate finance and restructuring tracks | F10: OCR | G10: Sept to Jan | H10: Creditor-side seats see crypto in downturns, not upcycles
A11: Guggenheim | B11: 1 - OCR | C11: NYC HQ | D11: Fintech coverage; no disclosed crypto credits surfaced 2024-26 | E11: Structured program | F11: OCR | G11: Sept to Jan | H11: Weakest crypto evidence in Tier 1; deprioritize unless networking comes cheap
A12: Jefferies | B12: 1 - OCR | C12: NYC HQ; full platform, larger associate class | D12: Three sell-sides in 15 months (NinjaTrader, Kiavi, Long Ridge) plus FTX creditors committee | E12: Structured program; conversion odds better than the EBs | F12: OCR | G12: Sept to Jan | H12: Best evidence-to-accessibility ratio in the formal cycle; promoted to co-lead in your portfolio
A13: Cantor Fitzgerald | B13: 2 - Direct | C13: NYC HQ; Brandon Lutnick era | D13: Twenty One (Tether/SoftBank), Securitize listing, Strive buy-side on Semler ($1.4B); bitcoin financing book | E13: Posts MBA-level roles; less structured; the digital assets group is the target | F13: NYC postings plus direct outreach; name the Semler mandate in the first note | G13: Rolling | H13: DAT derating is the franchise risk; the Strive M&A mandate shows diversification beyond SPACs
A14: FT Partners | B14: 2 - Direct | C14: SF HQ with NYC and London offices; a few hundred bankers | D14: Deribit ($2.9B), Hidden Road ($1.25B), WonderFi, Equiniti co-lead; the #1 sell-side franchise | E14: Hires associates directly via its Greenhouse board; apprenticeship model; postings cite blockchain and crypto knowledge | F14: Direct application plus outreach to the crypto vertical; founder-led (Steve McLaughlin) | G14: Rolling; start after the IBC resume book | H14: Highest crypto rep density of any seat that hires; culture is famously punishing, so diligence with former juniors before committing
... A34: Union Square Ventures | B34: 5 - Venture | C34: NYC; thesis-driven | D34: Early Coinbase backer; crypto thesis since 2013 | E34: Small; has run analyst and fellow programs | F34: CVF plus thoughtful written outreach; they reward writing | G34: CVF in Sept | H34: Broadest thesis of the set; crypto is one lens, not the mandate
A36: Named individuals are limited to publicly prominent, stable figures (founders, fund leads, co-CEOs); verify current roles on LinkedIn before any outreach, and fill in group-level contacts as you meet them. Compiled Aug 21, 2026 from the conversation's deal research.

Sheet Personal Angles
A1: Personal Angles: Your CV Mapped to the Target Set
A2: Each asset from the master CV, the one-liner that carries it, and where it lands | CBS Class of 2028
A3: Reference sheet: refine the one-liners in place as your story sharpens (yellow column F for notes).
A5: Asset / Experience | B5: The One-Liner | C5: Where It Lands | D5: How To Use It | E5: Cautions | F5: Refinements
A6: COR PRIME: in-house sell-side M&A (live) | B6: I am running a sell-side process from inside the company right now: transaction model, CIM, data room, buyer Q&A - with no mandated bank. | C6: Every IB conversation (abstracted); post-close: Talos, Castle Island, Broadhaven, Architect, FT Partners, Galaxy IB | D6: Until close, describe it generically ('leading an in-house strategic process at a regulated crypto prime-lending platform'). After close it becomes your headline story with names attached. | E6: NEVER name Project Optimus, the counterparty, or terms before signing/public disclosure. No Talos contact of any kind until close.
A7: ETC Group -> Bitwise sale | B7: I prepped the sale of a $2B-AUM crypto ETP issuer and was retained by the CEO through its acquisition by Bitwise - a deal that sits in this tracker's own Deal Evidence tab (Aug 2024). | C7: All crypto M&A conversations; VanEck Ventures (ETP house); Bitwise network; Architect Partners (they track every deal) | D7: You were inside one of the dataset's transactions. Use it to prove crypto M&A is not a thesis for you - it is a track record. | E7: Only public facts: the acquisition itself is public; valuation work and internal terms are not.
A8: Prime brokerage / lending domain | B8: Loan-book economics, funding costs, net interest margin, institutional counterparties - the market-structure layer most MBAs have never touched. | C8: Galaxy (all arms), Ripple (Hidden Road/Ripple Prime), Fintech Collective, Reciprocal, Hivemind, North Island | D8: Anchor your stablecoins / market-structure thesis in operating reality, not just research.
A9: Brasilpar: Gol/Smiles + 10 mandates | B9: Executed 10+ M&A mandates end-to-end at a Sao Paulo boutique, including advising Gol alongside Morgan Stanley on the take-in of its listed loyalty subsidiary. | C9: All Tier 1 OCR conversations; Jefferies, Evercore, Moelis; fairness-opinion story for Lazard | D9: This is the classic IB anchor story: public-company merger, fairness opinion, board exposure, at analyst age. | E9: Know the Smiles deal cold - structure, rationale, outcome - before the first coffee chat.
A10: ETC Group: ETP launches + tokenization build | B10: Launched an ETH staking ETP and an MSCI-benchmarked index ETP with regulatory approvals, and led a regulated equity-tokenization platform build. | C10: VanEck Ventures (perfect overlap), Figure, Circle, a16z crypto (Fund 5 tokenization thesis), Galaxy | D10: The tokenization thesis every 2026 fund cites - you have actually shipped against it. | E10: The tokenization platform was deprioritized by shareholders; frame as learning, have the 'why' ready.
A11: Nebula Ventures: family office principal | B11: Principal at a tech family office: interim COO of a portfolio company, board seat, org restructuring across five countries. | C11: VC platform/operating roles; corp dev (Kraken, Ripple integration angle); Portal and pre-seed funds (founder empathy) | D11: Proves you can be dropped into a company and run it - the corp dev integration and VC platform skillset.
A12: Quant digital-asset trading venture | B12: Co-founded a quantitative digital-asset trading venture (2024-present). | C12: Market-structure conversations; liquid-adjacent funds (CoinFund, Dragonfly, Hivemind); Syncracy research chats | D12: Signals market-native credibility; pairs with the Duke DeFi and INSEAD blockchain certifications. | E12: Be ready for sharp questions on strategy and PnL; do not overclaim scale.
A13: Brazil / LatAm + Portuguese | B13: Native Portuguese, Sao Paulo M&A training, dual-market fluency. | C13: Valor Capital (US-Brazil crossover); any fund discussing LatAm rails; the Tether/Adecoagro tender is a ready conversation piece | D13: Differentiated in NYC; almost no crypto-VC associates carry real LatAm execution experience.
A14: London / Europe network | B14: Four years operating in London crypto: ETC Group, Blockspace, COR PRIME, Deus X Capital orbit. | C14: Areta, Aream & Co, White Star DAF, KBW convergence plays; European LP and market-maker relationships | D14: Second geography of warm intros; useful for Europe-weighted mandates and funds.
A15: US citizen, no sponsorship | B15: US citizen; no visa sponsorship required. | C15: Everywhere - state it early with small firms | D15: Removes the #1 friction small firms have with international-profile candidates. Put it on every application.
A16: Certifications + writing surface | B16: Duke DeFi Specialization; INSEAD Blockchain, Cryptoassets & DeFi. | C16: Writing-first funds (Variant, USV, Portal); CVF application material | D16: Feed these into written outreach - the funds that reward writing are on your Stage 1 list. | E16: Certs support the story; they are not the story.
A17: Crypto-community fundraising (FIP cats) | B17: Founded a crypto-community initiative that financed FIP treatment for 50+ cats in Brazil. | C17: Any conversation that needs a human moment; consumer-crypto funds (6MV) | D17: Memorable, verifiable, and community-native - exactly the texture cold outreach usually lacks.
A18: CBS platform | B18: CBS Class of 2028; IBC + Fintech Club from day one; CVF opens ~Aug 28; gm3308@gsb.columbia.edu. | C18: Chris Dixon (Columbia BA/MA) is the marquee alumni hook; CVF is the VC-lane vehicle; CMC portal for OCR | D18: Work the Timeline tab: club fair first week, EIS sessions in Sept, IBC resume book Sept-Oct. | E18: Keep the VC endgame out of Tier 1 IB conversations (see VC Targets footer).
A20: Assets drawn from George_CV_Master.docx (Jul 2026). Bracketed [X] figures in the CV must be finalized before any line here is used live. Confidentiality rules: no Project Optimus references before signing; only public facts on the ETC Group/Bitwise transaction; abstract the COR PRIME process until close.

Sheet League Table
A1: Advisor League Table: Disclosed Crypto M&A Mandates, Jan 2024 to Aug 2026
A3: Firm | B3: Sell-side | C3: Buy-side | D3: Rx / DAT | E3: Total | F3: Marquee mandates | G3: Read
A4: FT Partners | B4: 4 | C4: 0 | D4: 0 | E4: 4 | F4: Deribit, Hidden Road, WonderFi, Equiniti (co-lead) | G4: #1 sell-side franchise; on nearly every marquee exit
A5: PJT Partners | B5: 2 | C5: 2 | D5: 1 | E5: 5 | F5: NinjaTrader + Reap (buy); Bitnomial + Core Scientific (sell); Core Scientific Ch. 11 | G5: Payward engine plus restructuring depth
A6: Moelis | B6: 1 | C6: 1 | D6: 3 | E6: 5 | F6: Voyager, Genesis, BlockFi debtors; Bitfarms buy; Core Scientific co-sell | G6: Restructuring franchise leader plus miner M&A
A7: Jefferies | B7: 3 | C7: 0 | D7: 1 | E7: 4 | F7: NinjaTrader, Kiavi, Long Ridge sell-sides; FTX creditors committee | G7: Steadiest all-rounder; easiest structured seat to win
A8: Cantor Fitzgerald | B8: 0 | C8: 1 | D8: 2 | E8: 3 | F8: Twenty One, Securitize; buy-side FA to Strive on Semler ($1.4B) | G8: DAT co-leader, now with a real M&A mandate
A9: Architect Partners | B9: 3 | C9: 0 | D9: 0 | E9: 3+ | F9: Coinme, Caleb & Brown, Magic Labs | G9: The mid-market crypto-native franchise
A10: Cohen & Co Capital Markets | B10: 1 | C10: 0 | D10: 2 | E10: 3 | F10: Stronghold sell; ProCap and Nakamoto lead FA | G10: DAT lane co-leader
A11: Galaxy Digital Partners | B11: 2 | C11: 0 | D11: 0 | E11: 2 | F11: Bitstamp, Aplo (both exclusive sell-sides) | G11: Crypto-native platform converting to real sell-sides
A12: LionTree | B12: 2 | C12: 0 | D12: 0 | E12: 2 | F12: Semler sell-side (exclusive); Equiniti syndicate seat | G12: Semler upgrades it from syndicate seat to lead credit
A13: Perella Weinberg | B13: 0 | C13: 0 | D13: 2 | E13: 2 | F13: FTX debtors, Celsius creditors | G13: Restructuring credibility on the biggest estates
A14: Areta | B14: 1 | C14: 1 | D14: 0 | E14: 15+ (self) | F14: Bulletin sell; Bridgepoint/ht.digital buy | G14: Emerging; Europe-weighted, smaller tickets; count is the firm's own claim
A15: Evercore | B15: 1 | C15: 0 | D15: 0 | E15: 1 | F15: Equiniti co-lead for Siris | G15: Real but episodic
... A24: XMS Capital | B24: 1 | C24: 0 | D24: 0 | E24: 1 | F24: Block Mining sell | G24: One-off
A26: BB reference:
A27: Goldman Sachs | B27: 2 | C27: 3 | D27: 0 | E27: 5 | F27: GTreasury, Reap-Asia (sell); CoreWeave, Bullish, NEOS (buy) | G27: Biggest tickets; crypto a subset of a huge platform
A28: Barclays | B28: 1 | C28: 3 | D28: 0 | E28: 4 | F28: NEOS (sell); Bitstamp, Kiavi, Long Ridge (buy) plus bridge financing | G28: Most active BB by a wide margin
A29: JPMorgan | B29: 1 | C29: 1 | D29: 0 | E29: 2 | F29: Adecoagro sell-side (Tether tender); Robinhood/WonderFi buy | G29: Two credits, both notable
A30: Citigroup | B30: 0 | C30: 0 | D30: 1 | E30: 1 | F30: Securitize FA and co-placement | G30: DAT entry
A32: Counts reflect disclosed financial advisor mandates only (announced Jan 2024 to Aug 2026), per press releases, firm tombstones, SEC filings, and deal research through Aug 21, 2026. Rx / DAT column combines restructuring and treasury/de-SPAC mandates. Undisclosed-advisor deals (Stripe/Bridge, Mastercard/BVNK, Talos/Coin Metrics, SBI/bitbank, and most sub-$100M deals) are excluded, so boutique counts understate true activity.

Sheet Deal Evidence
A1: Deal Evidence: Advisor Attributions by Transaction
A3: Announced | B3: Category | C3: Acquirer / Situation | D3: Target / Company | E3: Value | F3: Sell-side / Debtor FA | G3: Buy-side / Creditor FA | H3: Legal / Notes
A4: Apr 2024 | B4: Strategic | C4: Talos | D4: Cloudwall | E4: Undisclosed | F4: Not disclosed | G4: Not disclosed | H4: Risk management bolt-on
A5: May 2024 | B5: Strategic | C5: Talos | D5: Skolem | E5: Undisclosed | F5: Not disclosed | G5: Not disclosed | H5: Institutional DeFi infrastructure bolt-on
A6: Jun 2024 | B6: Strategic | C6: Robinhood | D6: Bitstamp | E6: $200M | F6: Galaxy Digital Partners (excl.) | G6: Barclays (excl.) | H6: Closed Jun 2025
A7: Jun 2024 | B7: Strategic | C7: CleanSpark | D7: GRIID Infrastructure | E7: $155M EV | F7: Lincoln International (FA + fairness) | G7: Not disclosed | H7: Cozen O'Connor (CleanSpark); Troutman Pepper (GRIID); closed Oct 2024
A8: Jul 2024 | B8: Strategic | C8: Riot Platforms | D8: Block Mining | E8: $92.5M | F8: XMS Capital (excl.) | G8: Stifel (excl.) | H8: Greenberg Traurig (Riot); Winston & Strawn (Block Mining)
A9: Aug 2024 | B9: Strategic | C9: Bitfarms | D9: Stronghold Digital | E9: $125M | F9: Cohen & Co Capital Markets | G9: Moelis
A10: Aug 2024 | B10: Strategic | C10: Bitwise | D10: ETC Group | E10: Undisclosed | F10: Not disclosed | G10: Not disclosed | H10: Latham (Bitwise); US-Europe ETP consolidation
A11: Oct 2024 | B11: Strategic | C11: Stripe | D11: Bridge | E11: $1.1B | F11: Not disclosed | G11: Not disclosed | H11: Wilson Sonsini (Stripe); largely relationship-driven
A12: Mar 2025 | B12: Strategic | C12: Kraken (Payward) | D12: NinjaTrader | E12: $1.5B | F12: Jefferies | G12: PJT Partners | H12: Jones Day, Lowenstein (Kraken); Choate, Katten (NinjaTrader)
A13: Mar 2025 | B13: Strategic | C13: Tether | D13: Adecoagro (~70%) | E13: ~$615.5M tender | F13: JPMorgan (excl.) | G13: Not disclosed | H13: Davis Polk, Elvinger Hoss (Adecoagro); McDermott (Tether); closed Apr 2025
A14: Apr 2025 | B14: Strategic | C14: Ripple | D14: Hidden Road | E14: $1.25B | F14: FT Partners | G14: Not disclosed | H14: Closed Oct 2025; rebranded Ripple Prime
A15: May 2025 | B15: Strategic | C15: Coinbase | D15: Deribit | E15: $2.9B ($3.9-4.3B at close) | F15: FT Partners | G15: Not disclosed | H15: Latham (Coinbase); Willkie (Deribit)
A16: May 2025 | B16: Strategic | C16: Robinhood | D16: WonderFi | E16: C$250M | F16: FT Partners | G16: JPMorgan | H16: Closed Jun 2026
A17: Jul 2025 | B17: Strategic | C17: CoreWeave | D17: Core Scientific | E17: $9B | F17: Moelis + PJT Partners | G17: Goldman Sachs | H17: Wachtell (Core Sci); Davis Polk, Kirkland (CoreWeave)
A18: Jul 2025 | B18: Strategic | C18: Talos | D18: Coin Metrics | E18: $100M+ | F18: Not disclosed | G18: Not disclosed | H18: Fenwick (Talos); direct CEO-to-CEO process per Fortune
A19: Aug 2025 | B19: Strategic | C19: Ripple | D19: Rail | E19: $200M | F19: Not disclosed | G19: Not disclosed
A20: Sep 2025 | B20: Strategic | C20: Coincheck | D20: Aplo | E20: Undisclosed | F20: Galaxy Digital Partners (excl.) | G20: Not disclosed | H20: Stock-for-stock; completed Oct 2025
A21: Oct 2025 | B21: Strategic | C21: Ripple | D21: GTreasury | E21: $1B | F21: Goldman Sachs (excl., for Hg) | G21: Not disclosed | H21: Morrison Foerster (Hg); Gunderson Dettmer (Ripple)
A22: Oct 2025 | B22: Strategic | C22: Coinbase | D22: Echo | E22: $375M | F22: Not disclosed | G22: Not disclosed | H22: Latham (Coinbase)
A23: Oct 2025 | B23: Strategic | C23: Kraken (Payward) | D23: Small Exchange | E23: $100M | F23: Not disclosed | G23: Not disclosed
A24: Jan 2026 | B24: Strategic | C24: Polygon Labs | D24: Coinme + Sequence | E24: ~$250M combined | F24: Architect Partners (Coinme, excl.) | G24: Not disclosed
A25: Feb 2026 | B25: Strategic | C25: Payward | D25: Magna | E25: Undisclosed | F25: Not disclosed | G25: Not disclosed
A26: Mar 2026 | B26: Strategic | C26: Mastercard | D26: BVNK | E26: Up to $1.8B | F26: Not disclosed | G26: Not disclosed | H26: Skadden (BVNK); Wilson Sonsini (Mastercard, privacy); closed Aug 3, 2026
A27: Apr 2026 | B27: Strategic | C27: Ripple | D27: BC Payments (Australia) | E27: Undisclosed | F27: Not disclosed | G27: Not disclosed | H27: License-driven
A28: Apr 2026 | B28: Strategic | C28: Payward | D28: Bitnomial | E28: Up to $550M | F28: PJT Partners (excl.) | G28: Not disclosed | H28: Haynes Boone, Katten (Bitnomial); Jones Day, Morrison Foerster (Payward); closed May 1
A29: Apr 2026 | B29: Strategic | C29: MARA | D29: Long Ridge (FTAI) | E29: $1.5B | F29: Jefferies + Lazard | G29: Barclays + Compass Point | H29: Paul Weiss, Sidley (MARA); Skadden (FTAI); Barclays bridge loan
A30: May 2026 | B30: Strategic | C30: Bullish | D30: Equiniti (Siris) | E30: $4.2B | F30: Evercore + FT Partners (leads); Wells Fargo, LionTree | G30: Goldman Sachs (excl.) | H30: Morgan Lewis, A&M (Bullish); Sidley (Siris)
A31: May 2026 | B31: Strategic | C31: Payward | D31: Reap | E31: Up to $600M | F31: CRB Securities + Goldman Sachs (Asia) | G31: PJT Partners | H31: Latham (Reap); Jones Day, Drew & Napier (Payward); closed Jul 1
A32: May 2026 | B32: Strategic | C32: Standard Chartered | D32: Zodia Custody | E32: Undisclosed | F32: Not disclosed | G32: Not disclosed | H32: Minority buyout; close targeted end Aug 2026
A33: Jun 2026 | B33: Strategic | C33: Figure | D33: Kiavi | E33: $717M | F33: Jefferies | G33: Barclays (excl., Figure/Sixth Street) | H33: Latham (Figure); Wilson Sonsini (Kiavi); Simpson Thacher (financing)
A34: Jun 2026 | B34: Strategic | C34: SBI Holdings | D34: bitbank | E34: $289M | F34: Not disclosed | G34: Not disclosed | H34: Close expected ~Oct 2026
A35: Jul 2026 | B35: Strategic | C35: Mirae Asset | D35: Korbit | E35: $91.5M | F35: Not disclosed | G35: Not disclosed | H35: Completed Jul 2026
A36: Jul 2026 | B36: Strategic | C36: Payward | D36: Magic Labs (wallet biz) | E36: Undisclosed | F36: Architect Partners (excl.) | G36: Not disclosed
A37: Aug 2026 | B37: Strategic | C37: OpenFX | D37: Global Ledger | E37: Undisclosed | F37: Not disclosed | G37: Not disclosed
A38: Aug 2026 | B38: Adjacent | C38: Goldman Sachs | D38: NEOS Investments | E38: Up to $2.25B | F38: Barclays (excl.) | G38: GS Global Banking & Markets | H38: Wachtell, Willkie (GS); Ropes & Gray (NEOS); crypto-adjacent ETF deal
A39: Jan 2024 | B39: Restructuring | C39: Ch. 11 emergence | D39: Core Scientific | E39: - | F39: PJT Partners (debtors) | G39: - | H39: Weil, AlixPartners
A40: Jan 2024 | B40: Restructuring | C40: Ch. 11 emergence | D40: Celsius | E40: - | F40: Centerview (debtors) | G40: Perella Weinberg (creditors) | H40: Kirkland, A&M; ~$20.1M Centerview fee allocation
A41: Aug 2024 | B41: Restructuring | C41: Plan completed | D41: Genesis Global | E41: - | F41: Moelis (debtors) | G41: Houlihan Lokey (creditors) | H41: Cleary, A&M; White & Case
A42: Oct 2024 | B42: Restructuring | C42: Plan confirmed | D42: FTX | E42: - | F42: Perella Weinberg (debtors) | G42: Jefferies (creditors) | H42: Sullivan & Cromwell, A&M; Paul Hastings, FTI
A43: 2023-24 | B43: Restructuring | C43: Wind-down | D43: Voyager Digital | E43: - | F43: Moelis (debtors) | G43: - | H43: Kirkland, BRG
A44: 2023-24 | B44: Restructuring | C44: Wind-down | D44: BlockFi | E44: - | F44: Moelis (debtors) | G44: - | H44: Kirkland, Haynes Boone, BRG
A45: Apr 2025 | B45: DAT / de-SPAC | C45: Cantor Equity Partners | D45: Twenty One Capital | E45: - | F45: Cantor Fitzgerald (FA + placement) | G45: - | H45: Skadden (Twenty One, Tether); NYSE: XXI Dec 2025
A46: Jun 2025 | B46: DAT / de-SPAC | C46: Columbus Circle Capital I | D46: ProCap BTC | E46: ~$1B | F46: Cohen & Co CM (excl. FA; co-placement with Clear Street) | G46: - | H46: Reed Smith; Ellenoff Grossman
A47: 2025 | B47: DAT / de-SPAC | C47: KindlyMD | D47: Nakamoto | E47: ~$710M | F47: Cohen & Co CM (lead FA + placement); 10X Capital | G47: - | H47: Reed Smith (Nakamoto)
A48: Sep 2025 | B48: DAT / de-SPAC | C48: Strive | D48: Semler Scientific | E48: ~$1.4B all-stock | F48: LionTree (excl.) | G48: Cantor Fitzgerald | H48: Davis Polk (Strive); Goodwin (Semler); first DAT stock-for-stock merger; closed Jan 2026
A49: Oct 2025 | B49: DAT / de-SPAC | C49: Cantor Equity Partners II | D49: Securitize | E49: $1.25B pre-money | F49: Citi (Securitize) | G49: Cantor Fitzgerald (CEPT) | H49: Davis Polk; Hughes Hubbard; NYSE: SECZ Jul 2026
A51: Attributions from company press releases, law firm and bank announcements, SEC filings, and Architect Partners M&A alerts. 'Not disclosed' means no public advisor attribution was found, not that no advisor was engaged. Restructuring engagements originated 2022-23 but concluded in the window shown.

Sheet Engagement Feed
A1: Engagement Feed: Content, Events, and CBS Actions
A2: Every hook named in the Aug 2026 research, plus the CBS-cycle actions from the Timeline tab | Engage BEFORE you reach out
A3: Fill in the yellow columns (G to H) as you subscribe, register, and attend.
A5: Source / Event | B5: Type | C5: Host / Firm | D5: Cadence / When | E5: Why It Matters / Action | F5: Priority | G5: Done? | H5: Notes
A6: CBS club fair - join IBC + Fintech Club | B6: CBS action | C6: Columbia Business School | D6: Aug 24 - early Sept | E6: Join both clubs immediately; get CMC portal access and pull the OCR employer roster against the Master Targets tab | F6: Now
A7: Columbia Venture Fellows (CVF) | B7: CBS action | C7: Columbia | D7: Opens ~Aug 28 | E7: The VC-lane vehicle; Galaxy Ventures, CoinFund, and USV are flagged CVF-compatible | F7: Now
A8: IBC prep program + resume book | B8: CBS action | C8: CBS Investment Banking Club | D8: Sept-Oct | E8: Submit to the resume book; lock the FIG/fintech story tied to your deal experience | F8: Now
A9: Employer information sessions | B9: CBS action | C9: Tier 1 firms via CMC | D9: From Sept | E9: Attend every Tier 1 session; log contacts in the lane tabs the same day | F9: Now
A10: Architect Partners M&A alerts | B10: Newsletter | C10: Architect Partners | D10: Per-deal | E10: Your ongoing market map: every alert names the advisors - feeds the Deal Evidence and League Table tabs | F10: Now
A11: Fintech Collective newsletter | B11: Newsletter | C11: Fintech Collective | D11: Recurring | E11: The stablecoins/payments canon ('The Dollar's New Avatar', 'Stablecoins Take the Lead'); reference it in outreach | F11: Now
A12: Galaxy Research | B12: Research | C12: Galaxy | D12: Recurring | E12: Underpins the best NYC stablecoins/market-structure conversation; read before any Galaxy touchpoint | F12: Now
A13: Variant thesis essays | B13: Research | C13: Variant | D13: Per-essay | E13: Writing-first outreach: respond to a live essay, don't cold-email | F13: Weekly
A14: USV thesis blog + AVC (Fred Wilson) | B14: Blog | C14: Union Square Ventures | D14: Recurring | E14: They reward writing; CVF plus a thoughtful written note is the entry | F14: Weekly
A15: a16z crypto research + State of Crypto | B15: Research | C15: a16z crypto | D15: Recurring + annual | E15: Fund 5 thesis language (stablecoins, tokenization, perp futures, prediction markets, AI agents); Dixon is the Columbia hook | F15: Weekly
A16: Placeholder research library | B16: Research | C16: Placeholder | D16: Archive | E16: Burniske's cryptoasset valuation frameworks are CVF-grade material | F16: Monthly
A17: Portal Ventures / Evan Fisher writing | B17: Blog | C17: Portal Ventures | D17: Recurring | E17: Fundamentals-driven framing; the most MBA-legible fund voice in the set | F17: Weekly
... A30: Consensys Tachyon / ecosystem events | B30: Events | C30: Consensys Mesh | D30: Recurring | E30: Brooklyn ecosystem surface; lower priority | F30: Monthly
A32: Hooks as named in the Aug 2026 research; CBS-cycle actions from the Timeline tab. Confirm 2026-27 conference dates when registration opens, and exact CBS dates on the CMC portal after orientation. Rule of thumb from the research: subscribe and engage BEFORE reaching out.

Sheet Timeline
A1: CBS Recruiting Cycle: Key Windows (Class of 2028)
A3: Window | B3: What Happens | C3: Your Moves
A4: Aug 24 to early Sept 2026 | B4: Orientation; club fair | C4: Join the Investment Banking Club and Fintech Club immediately; get CMC portal access and pull the current OCR employer roster against the Targets tab
A5: Sept 2026 | B5: Employer information sessions begin | C5: Attend every Tier 1 session; log contacts in the tracker the same day
A6: Sept to Oct 2026 | B6: IBC prep program; resume book deadline | C6: Submit your resume to the IBC book; lock the FIG / fintech story and tie it to your deal experience
A7: Oct to Nov 2026 | B7: Coffee chats, firm dinners, networking events | C7: Target 2 to 3 contacts per Tier 1 firm; start Tier 2 direct outreach in parallel
A8: Dec 2026 | B8: Closed-list invitations; resume drops open | C8: Apply through the CMC portal; prioritize firms where you have multiple advocates
A9: Jan 2027 | B9: Summer associate interviews (typically mid to late January) | C9: IBC mock interviews; technicals should be automatic before the holidays end
A10: Feb 2027 | B10: Offers and decisions | C10: Close your summer seat; keep Tier 2 and Tier 3 threads warm
A11: Mar to May 2027 | B11: Off-cycle and just-in-time hiring at boutiques | C11: Push Tier 3 conversations; crypto-native firms hire when deals land
A12: Summer 2027 | B12: Summer associate internship | C12: Convert; the return offer is the whole game
A13: Fall 2027 | B13: Full-time conversion and off-cycle moves | C13: If pivoting to a crypto-native firm for full time, this is the window
A15: Windows reflect the typical CBS IB cycle; confirm exact 2026-27 dates on the CMC portal after orientation.
